{"code":"002600","name":"领益智造","group":"","last_updated":"2026-07-01T07:27:21","meta":{"symbol":"002600","server":"110.41.147.114:7709","raw_start_date":"2023-03-10","raw_end_date":"2026-06-30","raw_rows":800,"end_trade_date":"2026-06-30","end_close":17.34,"quote":{"price":17.34,"last_close":15.76,"servertime":"15:32:55.002"},"adjust":"none"},"rows":[{"period_type":"trading_day","period_value":5,"label":"5交易日","target_date":"2026-06-24","base_trade_date":"2026-06-23","base_close":16.05,"end_trade_date":"2026-06-30","end_close":17.34,"return_pct":8.04},{"period_type":"trading_day","period_value":10,"label":"10交易日","target_date":"2026-06-16","base_trade_date":"2026-06-15","base_close":15.04,"end_trade_date":"2026-06-30","end_close":17.34,"return_pct":15.29},{"period_type":"trading_day","period_value":15,"label":"15交易日","target_date":"2026-06-09","base_trade_date":"2026-06-08","base_close":14.34,"end_trade_date":"2026-06-30","end_close":17.34,"return_pct":20.92},{"period_type":"month","period_value":1,"label":"1月","target_date":"2026-05-30","base_trade_date":"2026-05-29","base_close":14.55,"end_trade_date":"2026-06-30","end_close":17.34,"return_pct":19.18,"months":1},{"period_type":"month","period_value":2,"label":"2月","target_date":"2026-04-30","base_trade_date":"2026-04-29","base_close":14.03,"end_trade_date":"2026-06-30","end_close":17.34,"return_pct":23.59,"months":2},{"period_type":"month","period_value":3,"label":"3月","target_date":"2026-03-30","base_trade_date":"2026-03-27","base_close":13.17,"end_trade_date":"2026-06-30","end_close":17.34,"return_pct":31.66,"months":3},{"period_type":"month","period_value":4,"label":"4月","target_date":"2026-02-28","base_trade_date":"2026-02-27","base_close":15.38,"end_trade_date":"2026-06-30","end_close":17.34,"return_pct":12.74,"months":4},{"period_type":"month","period_value":5,"label":"5月","target_date":"2026-01-30","base_trade_date":"2026-01-29","base_close":14.89,"end_trade_date":"2026-06-30","end_close":17.34,"return_pct":16.45,"months":5},{"period_type":"month","period_value":6,"label":"6月","target_date":"2025-12-30","base_trade_date":"2025-12-29","base_close":15.56,"end_trade_date":"2026-06-30","end_close":17.34,"return_pct":11.44,"months":6},{"period_type":"month","period_value":7,"label":"7月","target_date":"2025-11-30","base_trade_date":"2025-11-28","base_close":13.9,"end_trade_date":"2026-06-30","end_close":17.34,"return_pct":24.75,"months":7},{"period_type":"month","period_value":8,"label":"8月","target_date":"2025-10-30","base_trade_date":"2025-10-29","base_close":16.19,"end_trade_date":"2026-06-30","end_close":17.34,"return_pct":7.1,"months":8},{"period_type":"month","period_value":9,"label":"9月","target_date":"2025-09-30","base_trade_date":"2025-09-29","base_close":16.18,"end_trade_date":"2026-06-30","end_close":17.34,"return_pct":7.17,"months":9},{"period_type":"month","period_value":10,"label":"10月","target_date":"2025-08-30","base_trade_date":"2025-08-29","base_close":15.54,"end_trade_date":"2026-06-30","end_close":17.34,"return_pct":11.58,"months":10},{"period_type":"month","period_value":11,"label":"11月","target_date":"2025-07-30","base_trade_date":"2025-07-29","base_close":9.17,"end_trade_date":"2026-06-30","end_close":17.34,"return_pct":89.09,"months":11},{"period_type":"month","period_value":12,"label":"12月","target_date":"2025-06-30","base_trade_date":"2025-06-27","base_close":8.51,"end_trade_date":"2026-06-30","end_close":17.34,"return_pct":103.76,"months":12},{"period_type":"month","period_value":13,"label":"13月","target_date":"2025-05-30","base_trade_date":"2025-05-29","base_close":8.23,"end_trade_date":"2026-06-30","end_close":17.34,"return_pct":110.69,"months":13},{"period_type":"month","period_value":14,"label":"14月","target_date":"2025-04-30","base_trade_date":"2025-04-29","base_close":7.74,"end_trade_date":"2026-06-30","end_close":17.34,"return_pct":124.03,"months":14},{"period_type":"month","period_value":15,"label":"15月","target_date":"2025-03-30","base_trade_date":"2025-03-28","base_close":9.16,"end_trade_date":"2026-06-30","end_close":17.34,"return_pct":89.3,"months":15},{"period_type":"month","period_value":16,"label":"16月","target_date":"2025-02-28","base_trade_date":"2025-02-27","base_close":10.43,"end_trade_date":"2026-06-30","end_close":17.34,"return_pct":66.25,"months":16},{"period_type":"month","period_value":17,"label":"17月","target_date":"2025-01-30","base_trade_date":"2025-01-27","base_close":8.51,"end_trade_date":"2026-06-30","end_close":17.34,"return_pct":103.76,"months":17},{"period_type":"month","period_value":18,"label":"18月","target_date":"2024-12-30","base_trade_date":"2024-12-27","base_close":8.54,"end_trade_date":"2026-06-30","end_close":17.34,"return_pct":103.04,"months":18},{"period_type":"month","period_value":19,"label":"19月","target_date":"2024-11-30","base_trade_date":"2024-11-29","base_close":8.59,"end_trade_date":"2026-06-30","end_close":17.34,"return_pct":101.86,"months":19},{"period_type":"month","period_value":20,"label":"20月","target_date":"2024-10-30","base_trade_date":"2024-10-29","base_close":8.76,"end_trade_date":"2026-06-30","end_close":17.34,"return_pct":97.95,"months":20},{"period_type":"month","period_value":21,"label":"21月","target_date":"2024-09-30","base_trade_date":"2024-09-27","base_close":6.88,"end_trade_date":"2026-06-30","end_close":17.34,"return_pct":152.03,"months":21},{"period_type":"month","period_value":22,"label":"22月","target_date":"2024-08-30","base_trade_date":"2024-08-29","base_close":7.62,"end_trade_date":"2026-06-30","end_close":17.34,"return_pct":127.56,"months":22},{"period_type":"month","period_value":23,"label":"23月","target_date":"2024-07-30","base_trade_date":"2024-07-29","base_close":6.91,"end_trade_date":"2026-06-30","end_close":17.34,"return_pct":150.94,"months":23},{"period_type":"month","period_value":24,"label":"24月","target_date":"2024-06-30","base_trade_date":"2024-06-28","base_close":7.12,"end_trade_date":"2026-06-30","end_close":17.34,"return_pct":143.54,"months":24}],"kline":[{"date":"2023-03-10","open":5.67,"high":5.77,"low":5.66,"close":5.67,"volume":284700.0,"amount":162859424.0},{"date":"2023-03-13","open":5.58,"high":5.71,"low":5.57,"close":5.71,"volume":312686.0,"amount":176721168.0},{"date":"2023-03-14","open":5.7,"high":5.74,"low":5.56,"close":5.68,"volume":276143.0,"amount":156111296.0},{"date":"2023-03-15","open":5.71,"high":5.89,"low":5.7,"close":5.74,"volume":353312.0,"amount":204941024.0},{"date":"2023-03-16","open":5.71,"high":5.78,"low":5.62,"close":5.64,"volume":260823.0,"amount":148482912.0},{"date":"2023-03-17","open":5.7,"high":5.86,"low":5.69,"close":5.73,"volume":419107.0,"amount":241855312.0},{"date":"2023-03-20","open":5.77,"high":5.9,"low":5.72,"close":5.86,"volume":640006.0,"amount":373289440.0},{"date":"2023-03-21","open":5.87,"high":6.26,"low":5.82,"close":6.02,"volume":1473675.0,"amount":890941248.0},{"date":"2023-03-22","open":5.9,"high":6.05,"low":5.83,"close":6.04,"volume":1121640.0,"amount":666737792.0},{"date":"2023-03-23","open":6.01,"high":6.2,"low":5.98,"close":6.14,"volume":962376.0,"amount":589609856.0},{"date":"2023-03-24","open":6.11,"high":6.32,"low":6.1,"close":6.25,"volume":1011077.0,"amount":629116608.0},{"date":"2023-03-27","open":6.23,"high":6.26,"low":6.06,"close":6.12,"volume":737685.0,"amount":453233152.0},{"date":"2023-03-28","open":6.11,"high":6.15,"low":6.05,"close":6.08,"volume":452836.0,"amount":275802624.0},{"date":"2023-03-29","open":6.08,"high":6.14,"low":6.01,"close":6.09,"volume":426841.0,"amount":259732672.0},{"date":"2023-03-30","open":6.08,"high":6.22,"low":6.06,"close":6.13,"volume":452778.0,"amount":278019328.0},{"date":"2023-03-31","open":6.11,"high":6.19,"low":6.03,"close":6.18,"volume":486552.0,"amount":297923552.0},{"date":"2023-04-03","open":6.17,"high":6.24,"low":6.13,"close":6.23,"volume":463029.0,"amount":286831328.0},{"date":"2023-04-04","open":6.23,"high":6.29,"low":6.16,"close":6.26,"volume":471633.0,"amount":293825120.0},{"date":"2023-04-06","open":6.22,"high":6.42,"low":6.2,"close":6.35,"volume":857534.0,"amount":543761216.0},{"date":"2023-04-07","open":6.38,"high":6.38,"low":6.15,"close":6.2,"volume":680642.0,"amount":425023296.0},{"date":"2023-04-10","open":6.2,"high":6.39,"low":6.2,"close":6.24,"volume":789175.0,"amount":496610048.0},{"date":"2023-04-11","open":6.2,"high":6.24,"low":6.12,"close":6.17,"volume":514864.0,"amount":317618592.0},{"date":"2023-04-12","open":6.27,"high":6.37,"low":6.25,"close":6.27,"volume":551647.0,"amount":347569440.0},{"date":"2023-04-13","open":6.22,"high":6.24,"low":6.07,"close":6.07,"volume":658536.0,"amount":403398368.0},{"date":"2023-04-14","open":6.1,"high":6.14,"low":5.98,"close":6.12,"volume":496089.0,"amount":301052864.0},{"date":"2023-04-17","open":6.11,"high":6.13,"low":6.02,"close":6.08,"volume":329200.0,"amount":200102384.0},{"date":"2023-04-18","open":6.07,"high":6.09,"low":5.93,"close":6.01,"volume":525687.0,"amount":315153568.0},{"date":"2023-04-19","open":5.99,"high":6.1,"low":5.98,"close":6.02,"volume":354973.0,"amount":214864976.0},{"date":"2023-04-20","open":6.01,"high":6.11,"low":6.01,"close":6.1,"volume":287788.0,"amount":174895344.0},{"date":"2023-04-21","open":6.08,"high":6.1,"low":5.76,"close":5.77,"volume":628798.0,"amount":370689696.0},{"date":"2023-04-24","open":5.78,"high":6.03,"low":5.78,"close":5.93,"volume":597035.0,"amount":354529216.0},{"date":"2023-04-25","open":5.93,"high":5.93,"low":5.62,"close":5.72,"volume":465099.0,"amount":267117472.0},{"date":"2023-04-26","open":5.71,"high":5.75,"low":5.58,"close":5.6,"volume":431666.0,"amount":243592032.0},{"date":"2023-04-27","open":5.58,"high":5.7,"low":5.52,"close":5.57,"volume":336439.0,"amount":187956384.0},{"date":"2023-04-28","open":5.63,"high":5.94,"low":5.6,"close":5.93,"volume":606303.0,"amount":353860736.0},{"date":"2023-05-04","open":6.1,"high":6.15,"low":5.85,"close":6.0,"volume":681680.0,"amount":406876768.0},{"date":"2023-05-05","open":6.05,"high":6.1,"low":5.96,"close":6.08,"volume":538114.0,"amount":325005760.0},{"date":"2023-05-08","open":6.07,"high":6.08,"low":5.97,"close":6.03,"volume":351219.0,"amount":211422848.0},{"date":"2023-05-09","open":6.0,"high":6.15,"low":5.91,"close":6.07,"volume":509757.0,"amount":308350624.0},{"date":"2023-05-10","open":6.02,"high":6.19,"low":5.99,"close":6.05,"volume":441463.0,"amount":268445344.0},{"date":"2023-05-11","open":6.05,"high":6.39,"low":6.02,"close":6.22,"volume":959552.0,"amount":596959808.0},{"date":"2023-05-12","open":6.12,"high":6.15,"low":5.84,"close":5.87,"volume":931524.0,"amount":555679552.0},{"date":"2023-05-15","open":5.86,"high":5.97,"low":5.68,"close":5.95,"volume":459075.0,"amount":267742240.0},{"date":"2023-05-16","open":5.93,"high":6.02,"low":5.83,"close":5.94,"volume":341330.0,"amount":202247952.0},{"date":"2023-05-17","open":5.92,"high":6.02,"low":5.89,"close":5.99,"volume":270132.0,"amount":160977392.0},{"date":"2023-05-18","open":6.01,"high":6.59,"low":6.0,"close":6.39,"volume":3070748.0,"amount":1973188096.0},{"date":"2023-05-19","open":6.35,"high":6.87,"low":6.32,"close":6.68,"volume":3640131.0,"amount":2412345856.0},{"date":"2023-05-22","open":6.81,"high":6.84,"low":6.33,"close":6.34,"volume":2433720.0,"amount":1577194880.0},{"date":"2023-05-23","open":6.34,"high":6.39,"low":6.2,"close":6.24,"volume":1070501.0,"amount":672089920.0},{"date":"2023-05-24","open":6.2,"high":6.23,"low":6.07,"close":6.08,"volume":1020096.0,"amount":624922432.0},{"date":"2023-05-25","open":6.07,"high":6.17,"low":5.79,"close":5.88,"volume":1158812.0,"amount":688073856.0},{"date":"2023-05-26","open":5.85,"high":5.99,"low":5.84,"close":5.94,"volume":619457.0,"amount":367199744.0},{"date":"2023-05-29","open":5.96,"high":6.34,"low":5.95,"close":6.21,"volume":1369960.0,"amount":851036864.0},{"date":"2023-05-30","open":6.15,"high":6.25,"low":6.07,"close":6.24,"volume":734044.0,"amount":451978016.0},{"date":"2023-05-31","open":6.22,"high":6.36,"low":6.19,"close":6.3,"volume":909584.0,"amount":572264768.0},{"date":"2023-06-01","open":6.31,"high":6.52,"low":6.24,"close":6.42,"volume":1084514.0,"amount":697604160.0},{"date":"2023-06-02","open":6.47,"high":6.53,"low":6.37,"close":6.44,"volume":861820.0,"amount":557109056.0},{"date":"2023-06-05","open":6.46,"high":6.49,"low":6.35,"close":6.41,"volume":568674.0,"amount":364434368.0},{"date":"2023-06-06","open":6.37,"high":6.4,"low":6.12,"close":6.15,"volume":784395.0,"amount":488156768.0},{"date":"2023-06-07","open":6.2,"high":6.29,"low":6.17,"close":6.25,"volume":475276.0,"amount":296880608.0},{"date":"2023-06-08","open":6.26,"high":6.27,"low":6.13,"close":6.23,"volume":480743.0,"amount":298600256.0},{"date":"2023-06-09","open":6.21,"high":6.38,"low":6.15,"close":6.37,"volume":970725.0,"amount":612978048.0},{"date":"2023-06-12","open":6.36,"high":6.57,"low":6.3,"close":6.5,"volume":844453.0,"amount":549171904.0},{"date":"2023-06-13","open":6.49,"high":6.61,"low":6.46,"close":6.57,"volume":717563.0,"amount":471673760.0},{"date":"2023-06-14","open":6.62,"high":6.67,"low":6.53,"close":6.63,"volume":734720.0,"amount":485104768.0},{"date":"2023-06-15","open":6.65,"high":6.7,"low":6.55,"close":6.6,"volume":465900.0,"amount":307220672.0},{"date":"2023-06-16","open":6.59,"high":6.77,"low":6.48,"close":6.72,"volume":697605.0,"amount":465826080.0},{"date":"2023-06-19","open":6.69,"high":6.82,"low":6.64,"close":6.79,"volume":542647.0,"amount":367251488.0},{"date":"2023-06-20","open":6.77,"high":6.85,"low":6.73,"close":6.76,"volume":469414.0,"amount":318417824.0},{"date":"2023-06-21","open":6.76,"high":6.83,"low":6.65,"close":6.66,"volume":509491.0,"amount":342772192.0},{"date":"2023-06-26","open":6.61,"high":6.69,"low":6.51,"close":6.53,"volume":522878.0,"amount":344744800.0},{"date":"2023-06-27","open":6.55,"high":6.74,"low":6.51,"close":6.68,"volume":452463.0,"amount":301713120.0},{"date":"2023-06-28","open":6.71,"high":6.73,"low":6.44,"close":6.64,"volume":440151.0,"amount":289045440.0},{"date":"2023-06-29","open":6.62,"high":7.05,"low":6.59,"close":6.88,"volume":1207798.0,"amount":831641024.0},{"date":"2023-06-30","open":6.95,"high":7.15,"low":6.85,"close":6.91,"volume":781255.0,"amount":542577856.0},{"date":"2023-07-03","open":6.93,"high":7.08,"low":6.78,"close":6.84,"volume":737420.0,"amount":506156064.0},{"date":"2023-07-04","open":6.87,"high":7.01,"low":6.86,"close":6.92,"volume":692368.0,"amount":480261664.0},{"date":"2023-07-05","open":6.93,"high":6.94,"low":6.78,"close":6.8,"volume":440422.0,"amount":300424832.0},{"date":"2023-07-06","open":6.81,"high":6.85,"low":6.74,"close":6.78,"volume":412983.0,"amount":280324384.0},{"date":"2023-07-07","open":6.69,"high":6.72,"low":6.49,"close":6.61,"volume":441914.0,"amount":291548800.0},{"date":"2023-07-10","open":6.61,"high":6.65,"low":6.55,"close":6.58,"volume":334767.0,"amount":220436064.0},{"date":"2023-07-11","open":6.56,"high":6.74,"low":6.55,"close":6.72,"volume":409944.0,"amount":274009248.0},{"date":"2023-07-12","open":6.7,"high":6.79,"low":6.58,"close":6.61,"volume":410903.0,"amount":274678304.0},{"date":"2023-07-13","open":6.82,"high":7.2,"low":6.78,"close":7.12,"volume":1836225.0,"amount":1295690752.0},{"date":"2023-07-14","open":7.12,"high":7.15,"low":7.02,"close":7.1,"volume":765928.0,"amount":542367104.0},{"date":"2023-07-17","open":7.04,"high":7.09,"low":6.93,"close":6.98,"volume":584754.0,"amount":407608864.0},{"date":"2023-07-18","open":6.98,"high":7.05,"low":6.91,"close":6.94,"volume":475103.0,"amount":331047296.0},{"date":"2023-07-19","open":6.95,"high":6.98,"low":6.84,"close":6.89,"volume":337390.0,"amount":232310768.0},{"date":"2023-07-20","open":6.9,"high":6.92,"low":6.66,"close":6.67,"volume":609654.0,"amount":411284224.0},{"date":"2023-07-21","open":6.7,"high":6.77,"low":6.6,"close":6.63,"volume":440786.0,"amount":294782624.0},{"date":"2023-07-24","open":6.6,"high":6.76,"low":6.53,"close":6.68,"volume":406173.0,"amount":271304480.0},{"date":"2023-07-25","open":6.73,"high":6.9,"low":6.63,"close":6.75,"volume":554610.0,"amount":373944800.0},{"date":"2023-07-26","open":6.73,"high":6.73,"low":6.23,"close":6.26,"volume":1241711.0,"amount":788214976.0},{"date":"2023-07-27","open":6.24,"high":6.31,"low":6.16,"close":6.18,"volume":633650.0,"amount":394030944.0},{"date":"2023-07-28","open":6.15,"high":6.22,"low":6.11,"close":6.19,"volume":437580.0,"amount":270725728.0},{"date":"2023-07-31","open":6.18,"high":6.26,"low":6.12,"close":6.15,"volume":666416.0,"amount":411803744.0},{"date":"2023-08-01","open":6.16,"high":6.19,"low":6.06,"close":6.17,"volume":592393.0,"amount":362715968.0},{"date":"2023-08-02","open":6.17,"high":6.17,"low":6.09,"close":6.11,"volume":342942.0,"amount":210005120.0},{"date":"2023-08-03","open":6.1,"high":6.15,"low":6.07,"close":6.12,"volume":387015.0,"amount":236279504.0},{"date":"2023-08-04","open":6.13,"high":6.24,"low":6.11,"close":6.22,"volume":540132.0,"amount":334800192.0},{"date":"2023-08-07","open":6.2,"high":6.25,"low":6.16,"close":6.21,"volume":438531.0,"amount":272274112.0},{"date":"2023-08-08","open":6.23,"high":6.3,"low":6.2,"close":6.23,"volume":456454.0,"amount":285083200.0},{"date":"2023-08-09","open":6.23,"high":6.26,"low":6.12,"close":6.15,"volume":398309.0,"amount":245567248.0},{"date":"2023-08-10","open":6.16,"high":6.18,"low":6.1,"close":6.13,"volume":272640.0,"amount":167184592.0},{"date":"2023-08-11","open":6.13,"high":6.15,"low":5.98,"close":5.99,"volume":374126.0,"amount":226557120.0},{"date":"2023-08-14","open":5.93,"high":6.02,"low":5.89,"close":6.01,"volume":357556.0,"amount":212717168.0},{"date":"2023-08-15","open":6.03,"high":6.05,"low":5.87,"close":5.9,"volume":356699.0,"amount":211679312.0},{"date":"2023-08-16","open":5.9,"high":5.9,"low":5.81,"close":5.82,"volume":281832.0,"amount":164698144.0},{"date":"2023-08-17","open":5.78,"high":5.9,"low":5.71,"close":5.88,"volume":279486.0,"amount":162965776.0},{"date":"2023-08-18","open":5.96,"high":5.99,"low":5.8,"close":5.81,"volume":312128.0,"amount":183554128.0},{"date":"2023-08-21","open":5.81,"high":5.89,"low":5.78,"close":5.79,"volume":315686.0,"amount":184121536.0},{"date":"2023-08-22","open":5.8,"high":5.84,"low":5.69,"close":5.82,"volume":438340.0,"amount":252903840.0},{"date":"2023-08-23","open":5.81,"high":5.82,"low":5.63,"close":5.64,"volume":397403.0,"amount":226176608.0},{"date":"2023-08-24","open":5.68,"high":5.77,"low":5.66,"close":5.7,"volume":323789.0,"amount":184884976.0},{"date":"2023-08-25","open":5.67,"high":5.72,"low":5.53,"close":5.57,"volume":419305.0,"amount":234397360.0},{"date":"2023-08-28","open":5.85,"high":5.89,"low":5.6,"close":5.63,"volume":646782.0,"amount":370234944.0},{"date":"2023-08-29","open":5.63,"high":5.89,"low":5.62,"close":5.88,"volume":835401.0,"amount":482878112.0},{"date":"2023-08-30","open":5.88,"high":5.99,"low":5.88,"close":5.95,"volume":589794.0,"amount":350746016.0},{"date":"2023-08-31","open":5.95,"high":6.1,"low":5.92,"close":6.02,"volume":651701.0,"amount":392928480.0},{"date":"2023-09-01","open":6.03,"high":6.05,"low":5.95,"close":5.99,"volume":359201.0,"amount":215052992.0},{"date":"2023-09-04","open":6.0,"high":6.08,"low":6.0,"close":6.08,"volume":467209.0,"amount":282364032.0},{"date":"2023-09-05","open":6.09,"high":6.15,"low":6.05,"close":6.08,"volume":485957.0,"amount":296299456.0},{"date":"2023-09-06","open":6.06,"high":6.11,"low":6.02,"close":6.07,"volume":453382.0,"amount":275249536.0},{"date":"2023-09-07","open":6.07,"high":6.09,"low":5.95,"close":5.96,"volume":456720.0,"amount":273691136.0},{"date":"2023-09-08","open":5.93,"high":5.99,"low":5.88,"close":5.93,"volume":257855.0,"amount":152949952.0},{"date":"2023-09-11","open":6.0,"high":6.06,"low":5.9,"close":6.03,"volume":481482.0,"amount":289195360.0},{"date":"2023-09-12","open":6.07,"high":6.11,"low":5.98,"close":6.04,"volume":571710.0,"amount":345563552.0},{"date":"2023-09-13","open":6.01,"high":6.02,"low":5.72,"close":5.82,"volume":688956.0,"amount":402854144.0},{"date":"2023-09-14","open":5.8,"high":5.85,"low":5.7,"close":5.75,"volume":398450.0,"amount":229195792.0},{"date":"2023-09-15","open":5.77,"high":5.83,"low":5.71,"close":5.73,"volume":340142.0,"amount":195600256.0},{"date":"2023-09-18","open":5.7,"high":5.85,"low":5.67,"close":5.76,"volume":398317.0,"amount":230026736.0},{"date":"2023-09-19","open":5.73,"high":5.76,"low":5.54,"close":5.58,"volume":480612.0,"amount":268852576.0},{"date":"2023-09-20","open":5.56,"high":5.62,"low":5.53,"close":5.54,"volume":281702.0,"amount":156879376.0},{"date":"2023-09-21","open":5.53,"high":5.62,"low":5.5,"close":5.56,"volume":321061.0,"amount":178750864.0},{"date":"2023-09-22","open":5.55,"high":5.74,"low":5.52,"close":5.73,"volume":528178.0,"amount":299749952.0},{"date":"2023-09-25","open":5.75,"high":5.79,"low":5.67,"close":5.7,"volume":342706.0,"amount":195664704.0},{"date":"2023-09-26","open":5.7,"high":5.74,"low":5.63,"close":5.63,"volume":271512.0,"amount":153632096.0},{"date":"2023-09-27","open":5.63,"high":5.67,"low":5.59,"close":5.61,"volume":283088.0,"amount":159349280.0},{"date":"2023-09-28","open":5.63,"high":5.75,"low":5.62,"close":5.72,"volume":541373.0,"amount":308146336.0},{"date":"2023-10-09","open":5.7,"high":5.93,"low":5.68,"close":5.88,"volume":718863.0,"amount":419608224.0},{"date":"2023-10-10","open":5.9,"high":6.0,"low":5.85,"close":5.98,"volume":608488.0,"amount":361153376.0},{"date":"2023-10-11","open":5.95,"high":6.15,"low":5.93,"close":6.1,"volume":766127.0,"amount":464683968.0},{"date":"2023-10-12","open":6.08,"high":6.12,"low":6.01,"close":6.04,"volume":483913.0,"amount":292616064.0},{"date":"2023-10-13","open":6.01,"high":6.12,"low":5.98,"close":6.05,"volume":419002.0,"amount":253970720.0},{"date":"2023-10-16","open":6.03,"high":6.06,"low":5.89,"close":5.92,"volume":411257.0,"amount":244897792.0},{"date":"2023-10-17","open":5.92,"high":5.98,"low":5.83,"close":5.86,"volume":370196.0,"amount":217239280.0},{"date":"2023-10-18","open":5.85,"high":5.86,"low":5.71,"close":5.73,"volume":394565.0,"amount":226946880.0},{"date":"2023-10-19","open":5.69,"high":5.81,"low":5.68,"close":5.71,"volume":578330.0,"amount":332841312.0},{"date":"2023-10-20","open":5.68,"high":5.71,"low":5.5,"close":5.5,"volume":512027.0,"amount":285900416.0},{"date":"2023-10-23","open":5.48,"high":5.5,"low":5.28,"close":5.37,"volume":545655.0,"amount":293562208.0},{"date":"2023-10-24","open":5.44,"high":5.49,"low":5.3,"close":5.39,"volume":470611.0,"amount":253290656.0},{"date":"2023-10-25","open":5.42,"high":5.6,"low":5.39,"close":5.57,"volume":606763.0,"amount":334660000.0},{"date":"2023-10-26","open":5.53,"high":5.8,"low":5.48,"close":5.78,"volume":750661.0,"amount":428271712.0},{"date":"2023-10-27","open":5.74,"high":6.03,"low":5.67,"close":6.01,"volume":892449.0,"amount":526192416.0},{"date":"2023-10-30","open":5.94,"high":6.09,"low":5.89,"close":6.05,"volume":1135507.0,"amount":684138752.0},{"date":"2023-10-31","open":6.01,"high":6.15,"low":6.0,"close":6.07,"volume":650749.0,"amount":395461120.0},{"date":"2023-11-01","open":6.05,"high":6.11,"low":5.99,"close":6.0,"volume":558101.0,"amount":336571392.0},{"date":"2023-11-02","open":6.01,"high":6.04,"low":5.88,"close":5.89,"volume":535505.0,"amount":318110080.0},{"date":"2023-11-03","open":5.93,"high":6.1,"low":5.9,"close":6.08,"volume":608731.0,"amount":366556704.0},{"date":"2023-11-06","open":6.3,"high":6.69,"low":6.28,"close":6.69,"volume":1697769.0,"amount":1109030912.0},{"date":"2023-11-07","open":6.76,"high":6.82,"low":6.57,"close":6.74,"volume":2870903.0,"amount":1917763712.0},{"date":"2023-11-08","open":6.7,"high":6.84,"low":6.67,"close":6.74,"volume":1415139.0,"amount":954762624.0},{"date":"2023-11-09","open":6.74,"high":6.79,"low":6.62,"close":6.64,"volume":865476.0,"amount":577144064.0},{"date":"2023-11-10","open":6.61,"high":6.79,"low":6.57,"close":6.74,"volume":1061690.0,"amount":709098496.0},{"date":"2023-11-13","open":6.97,"high":7.09,"low":6.78,"close":6.82,"volume":1488904.0,"amount":1026228160.0},{"date":"2023-11-14","open":6.84,"high":6.92,"low":6.74,"close":6.82,"volume":826551.0,"amount":564246080.0},{"date":"2023-11-15","open":6.99,"high":7.34,"low":6.85,"close":6.92,"volume":1265179.0,"amount":885802816.0},{"date":"2023-11-16","open":6.9,"high":6.97,"low":6.83,"close":6.83,"volume":706433.0,"amount":486072832.0},{"date":"2023-11-17","open":6.83,"high":6.88,"low":6.72,"close":6.78,"volume":638257.0,"amount":433475488.0},{"date":"2023-11-20","open":6.78,"high":6.8,"low":6.67,"close":6.7,"volume":735865.0,"amount":493902752.0},{"date":"2023-11-21","open":6.74,"high":6.82,"low":6.62,"close":6.66,"volume":683039.0,"amount":458791584.0},{"date":"2023-11-22","open":6.62,"high":6.68,"low":6.53,"close":6.53,"volume":521024.0,"amount":343639392.0},{"date":"2023-11-23","open":6.54,"high":6.75,"low":6.5,"close":6.72,"volume":674502.0,"amount":448570624.0},{"date":"2023-11-24","open":6.75,"high":6.9,"low":6.74,"close":6.8,"volume":1060611.0,"amount":722253504.0},{"date":"2023-11-27","open":6.79,"high":6.9,"low":6.71,"close":6.85,"volume":777584.0,"amount":529731424.0},{"date":"2023-11-28","open":7.1,"high":7.15,"low":6.71,"close":6.82,"volume":1212407.0,"amount":828146432.0},{"date":"2023-11-29","open":6.81,"high":6.88,"low":6.7,"close":6.72,"volume":939200.0,"amount":635393344.0},{"date":"2023-11-30","open":6.71,"high":6.75,"low":6.63,"close":6.69,"volume":577581.0,"amount":386309184.0},{"date":"2023-12-01","open":6.66,"high":6.78,"low":6.61,"close":6.74,"volume":459845.0,"amount":308092064.0},{"date":"2023-12-04","open":6.71,"high":6.85,"low":6.65,"close":6.7,"volume":564764.0,"amount":380428544.0},{"date":"2023-12-05","open":6.7,"high":6.71,"low":6.43,"close":6.46,"volume":844088.0,"amount":551921152.0},{"date":"2023-12-06","open":6.42,"high":6.59,"low":6.41,"close":6.54,"volume":500185.0,"amount":325284736.0},{"date":"2023-12-07","open":6.53,"high":6.6,"low":6.48,"close":6.49,"volume":407197.0,"amount":266146544.0},{"date":"2023-12-08","open":6.49,"high":6.61,"low":6.44,"close":6.49,"volume":544897.0,"amount":355019968.0},{"date":"2023-12-11","open":6.5,"high":6.75,"low":6.41,"close":6.73,"volume":773925.0,"amount":511560160.0},{"date":"2023-12-12","open":6.7,"high":6.8,"low":6.65,"close":6.77,"volume":606895.0,"amount":408817344.0},{"date":"2023-12-13","open":6.8,"high":6.82,"low":6.69,"close":6.7,"volume":340758.0,"amount":229709840.0},{"date":"2023-12-14","open":6.74,"high":6.77,"low":6.54,"close":6.55,"volume":485304.0,"amount":321780608.0},{"date":"2023-12-15","open":6.58,"high":6.68,"low":6.49,"close":6.52,"volume":403866.0,"amount":265407504.0},{"date":"2023-12-18","open":6.51,"high":6.54,"low":6.41,"close":6.46,"volume":346649.0,"amount":224407008.0},{"date":"2023-12-19","open":6.45,"high":6.67,"low":6.43,"close":6.63,"volume":544638.0,"amount":358665760.0},{"date":"2023-12-20","open":6.63,"high":6.73,"low":6.5,"close":6.61,"volume":651555.0,"amount":432546496.0},{"date":"2023-12-21","open":6.59,"high":6.63,"low":6.48,"close":6.55,"volume":540502.0,"amount":354364992.0},{"date":"2023-12-22","open":6.58,"high":6.62,"low":6.42,"close":6.45,"volume":526055.0,"amount":343105248.0},{"date":"2023-12-25","open":6.42,"high":6.52,"low":6.37,"close":6.47,"volume":441266.0,"amount":284158144.0},{"date":"2023-12-26","open":6.48,"high":6.48,"low":6.25,"close":6.32,"volume":453813.0,"amount":286325600.0},{"date":"2023-12-27","open":6.31,"high":6.6,"low":6.3,"close":6.54,"volume":614955.0,"amount":398653120.0},{"date":"2023-12-28","open":6.56,"high":6.61,"low":6.5,"close":6.53,"volume":496949.0,"amount":326106400.0},{"date":"2023-12-29","open":6.53,"high":6.82,"low":6.49,"close":6.76,"volume":741416.0,"amount":498981824.0},{"date":"2024-01-02","open":6.74,"high":6.82,"low":6.71,"close":6.76,"volume":572873.0,"amount":387883968.0},{"date":"2024-01-03","open":6.73,"high":6.75,"low":6.24,"close":6.29,"volume":1066811.0,"amount":686131584.0},{"date":"2024-01-04","open":6.24,"high":6.3,"low":6.12,"close":6.15,"volume":607798.0,"amount":376086016.0},{"date":"2024-01-05","open":6.16,"high":6.33,"low":6.05,"close":6.1,"volume":614940.0,"amount":379413472.0},{"date":"2024-01-08","open":6.05,"high":6.09,"low":5.83,"close":5.85,"volume":671079.0,"amount":398284352.0},{"date":"2024-01-09","open":5.89,"high":5.95,"low":5.73,"close":5.78,"volume":688370.0,"amount":401302720.0},{"date":"2024-01-10","open":5.78,"high":5.78,"low":5.65,"close":5.68,"volume":579534.0,"amount":329718496.0},{"date":"2024-01-11","open":5.67,"high":5.74,"low":5.61,"close":5.69,"volume":643547.0,"amount":365821056.0},{"date":"2024-01-12","open":5.68,"high":5.68,"low":5.55,"close":5.56,"volume":578227.0,"amount":322793696.0},{"date":"2024-01-15","open":5.55,"high":5.62,"low":5.46,"close":5.57,"volume":468726.0,"amount":259991584.0},{"date":"2024-01-16","open":5.55,"high":5.6,"low":5.46,"close":5.52,"volume":450374.0,"amount":248676688.0},{"date":"2024-01-17","open":5.5,"high":5.54,"low":5.36,"close":5.37,"volume":510120.0,"amount":277835840.0},{"date":"2024-01-18","open":5.36,"high":5.41,"low":5.22,"close":5.38,"volume":583981.0,"amount":309939872.0},{"date":"2024-01-19","open":5.4,"high":5.44,"low":5.34,"close":5.36,"volume":476915.0,"amount":257104608.0},{"date":"2024-01-22","open":5.4,"high":5.44,"low":4.96,"close":5.01,"volume":693950.0,"amount":360171456.0},{"date":"2024-01-23","open":5.03,"high":5.22,"low":5.0,"close":5.19,"volume":749695.0,"amount":384279744.0},{"date":"2024-01-24","open":5.21,"high":5.28,"low":4.98,"close":5.17,"volume":662040.0,"amount":337813792.0},{"date":"2024-01-25","open":5.17,"high":5.33,"low":5.11,"close":5.32,"volume":515409.0,"amount":270924736.0},{"date":"2024-01-26","open":5.34,"high":5.34,"low":5.16,"close":5.18,"volume":577777.0,"amount":302339232.0},{"date":"2024-01-29","open":5.21,"high":5.23,"low":5.03,"close":5.05,"volume":458792.0,"amount":233837504.0},{"date":"2024-01-30","open":5.01,"high":5.1,"low":4.89,"close":4.9,"volume":468675.0,"amount":234266944.0},{"date":"2024-01-31","open":4.89,"high":4.94,"low":4.73,"close":4.75,"volume":572679.0,"amount":275621696.0},{"date":"2024-02-01","open":4.73,"high":4.89,"low":4.68,"close":4.77,"volume":568533.0,"amount":272427200.0},{"date":"2024-02-02","open":4.77,"high":4.83,"low":4.41,"close":4.58,"volume":630053.0,"amount":292988864.0},{"date":"2024-02-05","open":4.58,"high":4.61,"low":4.26,"close":4.41,"volume":779680.0,"amount":346482688.0},{"date":"2024-02-06","open":4.39,"high":4.85,"low":4.3,"close":4.85,"volume":732442.0,"amount":342859168.0},{"date":"2024-02-07","open":4.87,"high":5.32,"low":4.84,"close":5.26,"volume":1454606.0,"amount":752657792.0},{"date":"2024-02-08","open":5.24,"high":5.59,"low":5.23,"close":5.26,"volume":1269486.0,"amount":684393728.0},{"date":"2024-02-19","open":5.31,"high":5.35,"low":5.11,"close":5.22,"volume":930728.0,"amount":485875296.0},{"date":"2024-02-20","open":5.2,"high":5.2,"low":5.11,"close":5.17,"volume":529083.0,"amount":272375200.0},{"date":"2024-02-21","open":5.15,"high":5.31,"low":5.07,"close":5.19,"volume":704316.0,"amount":367551904.0},{"date":"2024-02-22","open":5.16,"high":5.26,"low":5.15,"close":5.22,"volume":565500.0,"amount":293965952.0},{"date":"2024-02-23","open":5.25,"high":5.28,"low":5.16,"close":5.28,"volume":650087.0,"amount":339551392.0},{"date":"2024-02-26","open":5.28,"high":5.52,"low":5.26,"close":5.42,"volume":1100443.0,"amount":593677120.0},{"date":"2024-02-27","open":5.38,"high":5.7,"low":5.35,"close":5.69,"volume":1383899.0,"amount":769043712.0},{"date":"2024-02-28","open":5.71,"high":5.71,"low":5.26,"close":5.27,"volume":1611902.0,"amount":888226368.0},{"date":"2024-02-29","open":5.18,"high":5.49,"low":5.16,"close":5.49,"volume":1154424.0,"amount":621183808.0},{"date":"2024-03-01","open":5.49,"high":5.59,"low":5.46,"close":5.58,"volume":1073225.0,"amount":594437120.0},{"date":"2024-03-04","open":5.65,"high":5.68,"low":5.52,"close":5.62,"volume":1232797.0,"amount":691997376.0},{"date":"2024-03-05","open":5.57,"high":5.67,"low":5.48,"close":5.57,"volume":993988.0,"amount":555087360.0},{"date":"2024-03-06","open":5.57,"high":5.65,"low":5.45,"close":5.6,"volume":890918.0,"amount":496343040.0},{"date":"2024-03-07","open":5.64,"high":5.79,"low":5.52,"close":5.53,"volume":1182146.0,"amount":669003584.0},{"date":"2024-03-08","open":5.49,"high":5.65,"low":5.47,"close":5.64,"volume":896089.0,"amount":499060704.0},{"date":"2024-03-11","open":5.66,"high":5.68,"low":5.57,"close":5.67,"volume":764806.0,"amount":430524320.0},{"date":"2024-03-12","open":5.67,"high":5.71,"low":5.59,"close":5.65,"volume":792827.0,"amount":447289792.0},{"date":"2024-03-13","open":5.65,"high":5.71,"low":5.58,"close":5.64,"volume":742456.0,"amount":419254688.0},{"date":"2024-03-14","open":5.76,"high":5.76,"low":5.53,"close":5.59,"volume":872454.0,"amount":491442240.0},{"date":"2024-03-15","open":5.54,"high":5.69,"low":5.51,"close":5.69,"volume":759727.0,"amount":426279360.0},{"date":"2024-03-18","open":5.7,"high":5.83,"low":5.69,"close":5.82,"volume":1047382.0,"amount":602844992.0},{"date":"2024-03-19","open":5.77,"high":5.98,"low":5.75,"close":5.87,"volume":1276307.0,"amount":752846272.0},{"date":"2024-03-20","open":5.9,"high":5.92,"low":5.76,"close":5.84,"volume":980964.0,"amount":571054400.0},{"date":"2024-03-21","open":5.82,"high":5.85,"low":5.72,"close":5.74,"volume":729229.0,"amount":420623840.0},{"date":"2024-03-22","open":5.71,"high":5.77,"low":5.58,"close":5.64,"volume":761930.0,"amount":430591616.0},{"date":"2024-03-25","open":5.6,"high":5.7,"low":5.5,"close":5.51,"volume":719942.0,"amount":404191168.0},{"date":"2024-03-26","open":5.49,"high":5.56,"low":5.42,"close":5.5,"volume":521113.0,"amount":286464320.0},{"date":"2024-03-27","open":5.48,"high":5.49,"low":5.24,"close":5.24,"volume":586549.0,"amount":314575776.0},{"date":"2024-03-28","open":5.23,"high":5.54,"low":5.21,"close":5.45,"volume":743619.0,"amount":402954176.0},{"date":"2024-03-29","open":5.45,"high":5.49,"low":5.35,"close":5.49,"volume":423622.0,"amount":229585632.0},{"date":"2024-04-01","open":5.52,"high":5.64,"low":5.51,"close":5.62,"volume":628502.0,"amount":351510240.0},{"date":"2024-04-02","open":5.63,"high":5.64,"low":5.49,"close":5.53,"volume":547913.0,"amount":303439808.0},{"date":"2024-04-03","open":5.52,"high":5.52,"low":5.38,"close":5.43,"volume":425989.0,"amount":231698448.0},{"date":"2024-04-08","open":5.39,"high":5.45,"low":5.3,"close":5.32,"volume":488520.0,"amount":262534800.0},{"date":"2024-04-09","open":5.32,"high":5.36,"low":5.26,"close":5.35,"volume":372393.0,"amount":198204448.0},{"date":"2024-04-10","open":5.33,"high":5.34,"low":5.14,"close":5.18,"volume":457604.0,"amount":238362000.0},{"date":"2024-04-11","open":5.15,"high":5.26,"low":5.13,"close":5.17,"volume":378289.0,"amount":196981120.0},{"date":"2024-04-12","open":5.18,"high":5.26,"low":5.13,"close":5.14,"volume":432262.0,"amount":224095088.0},{"date":"2024-04-15","open":5.16,"high":5.29,"low":5.14,"close":5.25,"volume":667907.0,"amount":348864224.0},{"date":"2024-04-16","open":5.19,"high":5.27,"low":5.06,"close":5.07,"volume":619544.0,"amount":320185920.0},{"date":"2024-04-17","open":5.1,"high":5.25,"low":5.1,"close":5.25,"volume":577496.0,"amount":300860832.0},{"date":"2024-04-18","open":5.25,"high":5.32,"low":5.17,"close":5.25,"volume":547543.0,"amount":288294272.0},{"date":"2024-04-19","open":5.23,"high":5.24,"low":5.11,"close":5.13,"volume":522257.0,"amount":269704800.0},{"date":"2024-04-22","open":5.11,"high":5.18,"low":5.01,"close":5.09,"volume":367913.0,"amount":187530528.0},{"date":"2024-04-23","open":5.12,"high":5.16,"low":5.05,"close":5.07,"volume":355713.0,"amount":181107216.0},{"date":"2024-04-24","open":5.08,"high":5.24,"low":5.05,"close":5.24,"volume":500362.0,"amount":258824096.0},{"date":"2024-04-25","open":5.22,"high":5.27,"low":5.17,"close":5.19,"volume":348460.0,"amount":181416288.0},{"date":"2024-04-26","open":5.2,"high":5.32,"low":5.18,"close":5.32,"volume":513583.0,"amount":271364576.0},{"date":"2024-04-29","open":5.34,"high":5.48,"low":5.34,"close":5.47,"volume":726209.0,"amount":393345120.0},{"date":"2024-04-30","open":5.37,"high":5.4,"low":5.19,"close":5.21,"volume":1048409.0,"amount":550440768.0},{"date":"2024-05-06","open":5.28,"high":5.39,"low":5.23,"close":5.25,"volume":1007836.0,"amount":534129120.0},{"date":"2024-05-07","open":5.25,"high":5.26,"low":5.12,"close":5.15,"volume":810073.0,"amount":418882336.0},{"date":"2024-05-08","open":5.13,"high":5.14,"low":4.99,"close":4.99,"volume":933412.0,"amount":469912544.0},{"date":"2024-05-09","open":4.99,"high":5.15,"low":4.98,"close":5.11,"volume":771188.0,"amount":392429216.0},{"date":"2024-05-10","open":5.1,"high":5.12,"low":4.98,"close":5.0,"volume":774580.0,"amount":387814752.0},{"date":"2024-05-13","open":4.97,"high":4.99,"low":4.88,"close":4.92,"volume":571953.0,"amount":281828416.0},{"date":"2024-05-14","open":4.95,"high":5.04,"low":4.9,"close":4.93,"volume":657027.0,"amount":324800512.0},{"date":"2024-05-15","open":4.92,"high":4.95,"low":4.87,"close":4.88,"volume":494696.0,"amount":242194944.0},{"date":"2024-05-16","open":4.88,"high":4.92,"low":4.81,"close":4.82,"volume":696302.0,"amount":338390912.0},{"date":"2024-05-17","open":4.8,"high":4.88,"low":4.76,"close":4.87,"volume":598590.0,"amount":289400672.0},{"date":"2024-05-20","open":4.89,"high":4.95,"low":4.84,"close":4.93,"volume":698529.0,"amount":343206464.0},{"date":"2024-05-21","open":4.93,"high":4.94,"low":4.85,"close":4.87,"volume":450268.0,"amount":219763008.0},{"date":"2024-05-22","open":4.85,"high":4.91,"low":4.82,"close":4.9,"volume":528500.0,"amount":257242224.0},{"date":"2024-05-23","open":4.89,"high":4.89,"low":4.77,"close":4.78,"volume":600914.0,"amount":289216672.0},{"date":"2024-05-24","open":4.78,"high":4.82,"low":4.69,"close":4.69,"volume":419358.0,"amount":198788464.0},{"date":"2024-05-27","open":4.71,"high":4.75,"low":4.62,"close":4.75,"volume":446452.0,"amount":208811024.0},{"date":"2024-05-28","open":4.74,"high":4.78,"low":4.68,"close":4.69,"volume":384640.0,"amount":181670144.0},{"date":"2024-05-29","open":4.69,"high":4.75,"low":4.67,"close":4.7,"volume":380066.0,"amount":178974496.0},{"date":"2024-05-30","open":4.68,"high":4.82,"low":4.62,"close":4.79,"volume":662084.0,"amount":315637120.0},{"date":"2024-05-31","open":4.79,"high":5.1,"low":4.77,"close":4.93,"volume":1339649.0,"amount":658948608.0},{"date":"2024-06-03","open":4.93,"high":5.01,"low":4.84,"close":4.91,"volume":895217.0,"amount":440141248.0},{"date":"2024-06-04","open":4.86,"high":4.94,"low":4.75,"close":4.85,"volume":764455.0,"amount":368442976.0},{"date":"2024-06-05","open":4.82,"high":4.9,"low":4.79,"close":4.84,"volume":713005.0,"amount":346557280.0},{"date":"2024-06-06","open":4.86,"high":4.95,"low":4.82,"close":4.83,"volume":877699.0,"amount":427926752.0},{"date":"2024-06-07","open":4.84,"high":4.9,"low":4.72,"close":4.75,"volume":661025.0,"amount":317110944.0},{"date":"2024-06-11","open":4.67,"high":4.83,"low":4.64,"close":4.82,"volume":667379.0,"amount":316938112.0},{"date":"2024-06-12","open":4.9,"high":5.3,"low":4.9,"close":5.3,"volume":1433218.0,"amount":750664512.0},{"date":"2024-06-13","open":5.36,"high":5.43,"low":5.17,"close":5.2,"volume":3067492.0,"amount":1619532416.0},{"date":"2024-06-14","open":5.18,"high":5.24,"low":5.05,"close":5.12,"volume":1949488.0,"amount":998225792.0},{"date":"2024-06-17","open":5.08,"high":5.63,"low":5.07,"close":5.63,"volume":3262588.0,"amount":1777446144.0},{"date":"2024-06-18","open":5.61,"high":5.78,"low":5.52,"close":5.67,"volume":4332188.0,"amount":2455141632.0},{"date":"2024-06-19","open":5.61,"high":5.68,"low":5.49,"close":5.58,"volume":2156580.0,"amount":1201666560.0},{"date":"2024-06-20","open":5.82,"high":5.99,"low":5.65,"close":5.65,"volume":3533450.0,"amount":2046603776.0},{"date":"2024-06-21","open":5.57,"high":5.78,"low":5.51,"close":5.7,"volume":2344432.0,"amount":1330209792.0},{"date":"2024-06-24","open":5.59,"high":5.8,"low":5.48,"close":5.54,"volume":1970208.0,"amount":1113757184.0},{"date":"2024-06-25","open":5.51,"high":5.71,"low":5.46,"close":5.62,"volume":1861760.0,"amount":1040725120.0},{"date":"2024-06-26","open":5.56,"high":6.18,"low":5.44,"close":6.06,"volume":3332307.0,"amount":1956795008.0},{"date":"2024-06-27","open":5.97,"high":6.67,"low":5.95,"close":6.47,"volume":5220746.0,"amount":3383730176.0},{"date":"2024-06-28","open":6.35,"high":7.12,"low":6.32,"close":7.12,"volume":5955569.0,"amount":4108493312.0},{"date":"2024-07-01","open":7.0,"high":7.09,"low":6.73,"close":6.81,"volume":4776907.0,"amount":3265771264.0},{"date":"2024-07-02","open":6.83,"high":6.94,"low":6.56,"close":6.64,"volume":3927213.0,"amount":2645685248.0},{"date":"2024-07-03","open":6.6,"high":6.77,"low":6.41,"close":6.46,"volume":3512973.0,"amount":2291886080.0},{"date":"2024-07-04","open":6.41,"high":6.58,"low":6.33,"close":6.42,"volume":2814088.0,"amount":1815944960.0},{"date":"2024-07-05","open":6.44,"high":6.68,"low":6.27,"close":6.58,"volume":3151476.0,"amount":2049279232.0},{"date":"2024-07-08","open":6.68,"high":7.24,"low":6.62,"close":7.2,"volume":5177772.0,"amount":3625534720.0},{"date":"2024-07-09","open":7.03,"high":7.8,"low":6.96,"close":7.55,"volume":4759584.0,"amount":3498092288.0},{"date":"2024-07-10","open":7.44,"high":7.6,"low":7.31,"close":7.47,"volume":2929827.0,"amount":2181169664.0},{"date":"2024-07-11","open":7.53,"high":7.75,"low":7.29,"close":7.56,"volume":3725724.0,"amount":2801363200.0},{"date":"2024-07-12","open":7.21,"high":7.32,"low":7.11,"close":7.23,"volume":2676070.0,"amount":1932181120.0},{"date":"2024-07-15","open":7.24,"high":7.33,"low":6.89,"close":7.12,"volume":2272453.0,"amount":1606610432.0},{"date":"2024-07-16","open":7.13,"high":7.77,"low":7.12,"close":7.64,"volume":3978969.0,"amount":2943572992.0},{"date":"2024-07-17","open":7.5,"high":7.52,"low":7.15,"close":7.16,"volume":2723196.0,"amount":1989679360.0},{"date":"2024-07-18","open":6.81,"high":7.06,"low":6.68,"close":7.01,"volume":2530093.0,"amount":1737888896.0},{"date":"2024-07-19","open":6.87,"high":7.03,"low":6.76,"close":6.78,"volume":2055424.0,"amount":1410112128.0},{"date":"2024-07-22","open":6.78,"high":6.86,"low":6.54,"close":6.78,"volume":2054176.0,"amount":1373695488.0},{"date":"2024-07-23","open":6.78,"high":6.88,"low":6.58,"close":6.6,"volume":1625696.0,"amount":1089454976.0},{"date":"2024-07-24","open":6.58,"high":6.7,"low":6.4,"close":6.43,"volume":1592817.0,"amount":1036737280.0},{"date":"2024-07-25","open":6.37,"high":6.38,"low":6.12,"close":6.26,"volume":1826548.0,"amount":1136743936.0},{"date":"2024-07-26","open":6.25,"high":6.75,"low":6.22,"close":6.59,"volume":2108865.0,"amount":1375275392.0},{"date":"2024-07-29","open":6.58,"high":7.1,"low":6.42,"close":6.91,"volume":2736489.0,"amount":1877975168.0},{"date":"2024-07-30","open":6.85,"high":6.96,"low":6.69,"close":6.8,"volume":2072408.0,"amount":1412741376.0},{"date":"2024-07-31","open":6.76,"high":7.33,"low":6.76,"close":7.2,"volume":2812341.0,"amount":1999213312.0},{"date":"2024-08-01","open":7.2,"high":7.29,"low":7.01,"close":7.18,"volume":1946931.0,"amount":1387937664.0},{"date":"2024-08-02","open":7.0,"high":7.23,"low":6.78,"close":6.82,"volume":2032243.0,"amount":1413646720.0},{"date":"2024-08-05","open":6.58,"high":6.66,"low":6.24,"close":6.25,"volume":2185016.0,"amount":1400946432.0},{"date":"2024-08-06","open":6.44,"high":6.57,"low":6.34,"close":6.48,"volume":1475905.0,"amount":949901888.0},{"date":"2024-08-07","open":6.48,"high":6.55,"low":6.36,"close":6.43,"volume":1032111.0,"amount":665537536.0},{"date":"2024-08-08","open":6.39,"high":6.85,"low":6.3,"close":6.67,"volume":1906752.0,"amount":1263164928.0},{"date":"2024-08-09","open":6.73,"high":6.86,"low":6.62,"close":6.68,"volume":1402453.0,"amount":944232384.0},{"date":"2024-08-12","open":6.69,"high":6.95,"low":6.66,"close":6.72,"volume":1443573.0,"amount":980910336.0},{"date":"2024-08-13","open":6.7,"high":6.87,"low":6.62,"close":6.79,"volume":1170945.0,"amount":788441600.0},{"date":"2024-08-14","open":6.79,"high":6.85,"low":6.6,"close":6.74,"volume":1024116.0,"amount":691305280.0},{"date":"2024-08-15","open":6.7,"high":6.94,"low":6.7,"close":6.77,"volume":1259735.0,"amount":858206144.0},{"date":"2024-08-16","open":6.8,"high":7.0,"low":6.76,"close":6.79,"volume":1558827.0,"amount":1072671040.0},{"date":"2024-08-19","open":6.7,"high":6.89,"low":6.62,"close":6.64,"volume":1205944.0,"amount":809064576.0},{"date":"2024-08-20","open":6.64,"high":6.7,"low":6.48,"close":6.51,"volume":960507.0,"amount":629518336.0},{"date":"2024-08-21","open":6.49,"high":7.16,"low":6.44,"close":7.16,"volume":3316535.0,"amount":2323420928.0},{"date":"2024-08-22","open":7.14,"high":7.25,"low":6.91,"close":7.08,"volume":2911450.0,"amount":2055247104.0},{"date":"2024-08-23","open":7.06,"high":7.29,"low":6.81,"close":7.18,"volume":2534963.0,"amount":1792217344.0},{"date":"2024-08-26","open":7.25,"high":7.48,"low":7.02,"close":7.31,"volume":2868962.0,"amount":2081804416.0},{"date":"2024-08-27","open":7.21,"high":7.25,"low":6.79,"close":6.83,"volume":2240128.0,"amount":1560908928.0},{"date":"2024-08-28","open":6.73,"high":7.06,"low":6.7,"close":6.93,"volume":1503739.0,"amount":1040069248.0},{"date":"2024-08-29","open":6.85,"high":7.62,"low":6.81,"close":7.62,"volume":3632296.0,"amount":2670458112.0},{"date":"2024-08-30","open":7.76,"high":8.38,"low":7.68,"close":8.38,"volume":4557422.0,"amount":3692377344.0},{"date":"2024-09-02","open":8.59,"high":8.59,"low":7.94,"close":7.98,"volume":5266802.0,"amount":4305173504.0},{"date":"2024-09-03","open":7.8,"high":8.04,"low":7.66,"close":7.94,"volume":3167899.0,"amount":2497189120.0},{"date":"2024-09-04","open":7.7,"high":7.75,"low":7.24,"close":7.44,"volume":3606941.0,"amount":2691164672.0},{"date":"2024-09-05","open":7.35,"high":7.45,"low":7.27,"close":7.38,"volume":2255335.0,"amount":1658036480.0},{"date":"2024-09-06","open":7.39,"high":7.53,"low":7.17,"close":7.21,"volume":2557757.0,"amount":1869510016.0},{"date":"2024-09-09","open":7.08,"high":7.24,"low":6.93,"close":7.1,"volume":1909559.0,"amount":1346206848.0},{"date":"2024-09-10","open":7.01,"high":7.02,"low":6.42,"close":6.78,"volume":2871142.0,"amount":1918272640.0},{"date":"2024-09-11","open":6.71,"high":6.81,"low":6.46,"close":6.5,"volume":2095240.0,"amount":1379696128.0},{"date":"2024-09-12","open":6.55,"high":6.62,"low":6.26,"close":6.28,"volume":2195581.0,"amount":1397148160.0},{"date":"2024-09-13","open":6.28,"high":6.45,"low":6.21,"close":6.21,"volume":1907891.0,"amount":1208348672.0},{"date":"2024-09-18","open":6.13,"high":6.2,"low":5.96,"close":6.04,"volume":1823423.0,"amount":1102435456.0},{"date":"2024-09-19","open":6.1,"high":6.17,"low":6.05,"close":6.1,"volume":1728224.0,"amount":1056964992.0},{"date":"2024-09-20","open":6.18,"high":6.47,"low":6.15,"close":6.32,"volume":2682051.0,"amount":1700956032.0},{"date":"2024-09-23","open":6.21,"high":6.36,"low":6.09,"close":6.12,"volume":1851701.0,"amount":1145066240.0},{"date":"2024-09-24","open":6.12,"high":6.56,"low":5.98,"close":6.51,"volume":3157476.0,"amount":1986344960.0},{"date":"2024-09-25","open":6.52,"high":6.7,"low":6.35,"close":6.4,"volume":3060205.0,"amount":1994440064.0},{"date":"2024-09-26","open":6.31,"high":6.51,"low":6.24,"close":6.49,"volume":2327813.0,"amount":1484725248.0},{"date":"2024-09-27","open":6.5,"high":7.04,"low":6.5,"close":6.88,"volume":3623435.0,"amount":2440222464.0},{"date":"2024-09-30","open":7.13,"high":7.56,"low":7.0,"close":7.51,"volume":4120875.0,"amount":3002367488.0},{"date":"2024-10-08","open":8.26,"high":8.26,"low":7.41,"close":8.11,"volume":4944455.0,"amount":3901120000.0},{"date":"2024-10-09","open":7.78,"high":7.79,"low":7.3,"close":7.3,"volume":3394531.0,"amount":2530268160.0},{"date":"2024-10-10","open":7.2,"high":8.03,"low":7.16,"close":7.96,"volume":6085278.0,"amount":4767996416.0},{"date":"2024-10-11","open":7.5,"high":7.59,"low":7.16,"close":7.23,"volume":3900548.0,"amount":2872712960.0},{"date":"2024-10-14","open":7.05,"high":7.95,"low":6.97,"close":7.95,"volume":4575426.0,"amount":3478797056.0},{"date":"2024-10-15","open":7.96,"high":8.19,"low":7.76,"close":7.87,"volume":4057971.0,"amount":3251313664.0},{"date":"2024-10-16","open":7.66,"high":8.12,"low":7.55,"close":7.68,"volume":3051760.0,"amount":2374746624.0},{"date":"2024-10-17","open":7.67,"high":8.3,"low":7.65,"close":8.07,"volume":4292190.0,"amount":3464596224.0},{"date":"2024-10-18","open":7.91,"high":8.88,"low":7.84,"close":8.44,"volume":5569208.0,"amount":4647153664.0},{"date":"2024-10-21","open":8.5,"high":8.8,"low":8.19,"close":8.47,"volume":4920749.0,"amount":4181784320.0},{"date":"2024-10-22","open":8.31,"high":9.32,"low":8.21,"close":9.02,"volume":6444165.0,"amount":5776688640.0},{"date":"2024-10-23","open":8.8,"high":9.53,"low":8.62,"close":8.93,"volume":5886841.0,"amount":5309586944.0},{"date":"2024-10-24","open":8.73,"high":8.76,"low":8.45,"close":8.52,"volume":3348053.0,"amount":2863052288.0},{"date":"2024-10-25","open":8.5,"high":8.66,"low":8.45,"close":8.52,"volume":2487290.0,"amount":2119223808.0},{"date":"2024-10-28","open":8.62,"high":8.81,"low":8.41,"close":8.73,"volume":2855168.0,"amount":2458566400.0},{"date":"2024-10-29","open":8.73,"high":9.26,"low":8.64,"close":8.76,"volume":4147302.0,"amount":3701755392.0},{"date":"2024-10-30","open":8.69,"high":9.24,"low":8.51,"close":9.14,"volume":4026983.0,"amount":3587042816.0},{"date":"2024-10-31","open":9.41,"high":9.41,"low":8.83,"close":9.02,"volume":4241594.0,"amount":3839754240.0},{"date":"2024-11-01","open":8.87,"high":8.91,"low":8.3,"close":8.4,"volume":3223644.0,"amount":2763843072.0},{"date":"2024-11-04","open":8.3,"high":8.62,"low":8.28,"close":8.5,"volume":1574459.0,"amount":1333991936.0},{"date":"2024-11-05","open":8.49,"high":9.29,"low":8.43,"close":9.11,"volume":4240333.0,"amount":3803042048.0},{"date":"2024-11-06","open":9.12,"high":9.16,"low":8.76,"close":8.84,"volume":3522815.0,"amount":3155579648.0},{"date":"2024-11-07","open":8.68,"high":8.74,"low":8.45,"close":8.68,"volume":2808775.0,"amount":2413667072.0},{"date":"2024-11-08","open":8.73,"high":8.93,"low":8.59,"close":8.62,"volume":2908057.0,"amount":2540194560.0},{"date":"2024-11-11","open":8.54,"high":9.1,"low":8.45,"close":8.96,"volume":3735547.0,"amount":3279015424.0},{"date":"2024-11-12","open":8.9,"high":9.41,"low":8.85,"close":9.07,"volume":4635090.0,"amount":4221715456.0},{"date":"2024-11-13","open":8.95,"high":9.59,"low":8.62,"close":9.59,"volume":5670320.0,"amount":5187789824.0},{"date":"2024-11-14","open":9.5,"high":9.95,"low":8.9,"close":8.95,"volume":4640481.0,"amount":4325054464.0},{"date":"2024-11-15","open":8.97,"high":9.28,"low":8.8,"close":8.94,"volume":3118047.0,"amount":2820910080.0},{"date":"2024-11-18","open":8.94,"high":8.96,"low":8.06,"close":8.15,"volume":2931724.0,"amount":2473747456.0},{"date":"2024-11-19","open":8.01,"high":8.33,"low":7.98,"close":8.3,"volume":2058774.0,"amount":1682550912.0},{"date":"2024-11-20","open":8.29,"high":8.49,"low":8.2,"close":8.39,"volume":1646474.0,"amount":1377171584.0},{"date":"2024-11-21","open":8.3,"high":8.44,"low":8.21,"close":8.28,"volume":1413493.0,"amount":1173906944.0},{"date":"2024-11-22","open":8.25,"high":8.69,"low":8.21,"close":8.28,"volume":2621873.0,"amount":2228527360.0},{"date":"2024-11-25","open":8.28,"high":8.35,"low":7.84,"close":8.01,"volume":2097448.0,"amount":1669111040.0},{"date":"2024-11-26","open":7.98,"high":8.2,"low":7.92,"close":7.95,"volume":1142975.0,"amount":916721216.0},{"date":"2024-11-27","open":7.92,"high":8.4,"low":7.67,"close":8.33,"volume":2324135.0,"amount":1890507776.0},{"date":"2024-11-28","open":8.33,"high":8.55,"low":8.2,"close":8.24,"volume":1553889.0,"amount":1293962112.0},{"date":"2024-11-29","open":8.18,"high":8.68,"low":8.16,"close":8.59,"volume":2435219.0,"amount":2065280000.0},{"date":"2024-12-02","open":8.91,"high":9.08,"low":8.74,"close":8.83,"volume":3055859.0,"amount":2711314432.0},{"date":"2024-12-03","open":8.76,"high":8.85,"low":8.58,"close":8.67,"volume":1552848.0,"amount":1350679552.0},{"date":"2024-12-04","open":8.68,"high":8.99,"low":8.51,"close":8.8,"volume":2146704.0,"amount":1879708544.0},{"date":"2024-12-05","open":8.7,"high":8.86,"low":8.63,"close":8.74,"volume":1403649.0,"amount":1227959680.0},{"date":"2024-12-06","open":8.75,"high":8.99,"low":8.75,"close":8.92,"volume":2258140.0,"amount":2003411712.0},{"date":"2024-12-09","open":9.02,"high":9.04,"low":8.7,"close":8.77,"volume":1848399.0,"amount":1634658944.0},{"date":"2024-12-10","open":9.01,"high":9.45,"low":8.87,"close":9.05,"volume":3490576.0,"amount":3184096256.0},{"date":"2024-12-11","open":9.07,"high":9.77,"low":8.96,"close":9.57,"volume":4560332.0,"amount":4288402688.0},{"date":"2024-12-12","open":9.5,"high":9.55,"low":9.18,"close":9.28,"volume":2940476.0,"amount":2738457088.0},{"date":"2024-12-13","open":9.22,"high":9.45,"low":9.1,"close":9.11,"volume":2596737.0,"amount":2404921856.0},{"date":"2024-12-16","open":9.01,"high":9.02,"low":8.72,"close":8.79,"volume":1855894.0,"amount":1635649408.0},{"date":"2024-12-17","open":8.72,"high":8.93,"low":8.66,"close":8.73,"volume":1282999.0,"amount":1126002048.0},{"date":"2024-12-18","open":8.78,"high":8.86,"low":8.66,"close":8.77,"volume":979682.0,"amount":858108992.0},{"date":"2024-12-19","open":8.57,"high":8.98,"low":8.52,"close":8.88,"volume":1962918.0,"amount":1731988096.0},{"date":"2024-12-20","open":8.88,"high":9.13,"low":8.8,"close":8.98,"volume":1836771.0,"amount":1650424064.0},{"date":"2024-12-23","open":8.98,"high":9.05,"low":8.46,"close":8.49,"volume":1683698.0,"amount":1464093568.0},{"date":"2024-12-24","open":8.5,"high":8.64,"low":8.46,"close":8.6,"volume":1041930.0,"amount":891783296.0},{"date":"2024-12-25","open":8.59,"high":8.61,"low":8.25,"close":8.3,"volume":1214266.0,"amount":1018161856.0},{"date":"2024-12-26","open":8.23,"high":8.6,"low":8.21,"close":8.54,"volume":1188794.0,"amount":1009910528.0},{"date":"2024-12-27","open":8.53,"high":8.74,"low":8.49,"close":8.54,"volume":1172224.0,"amount":1010767808.0},{"date":"2024-12-30","open":8.54,"high":8.56,"low":8.3,"close":8.32,"volume":1136324.0,"amount":955028864.0},{"date":"2024-12-31","open":8.33,"high":8.37,"low":7.99,"close":8.0,"volume":1282749.0,"amount":1044661760.0},{"date":"2025-01-02","open":7.97,"high":8.14,"low":7.72,"close":7.82,"volume":1146436.0,"amount":910359232.0},{"date":"2025-01-03","open":7.82,"high":7.89,"low":7.61,"close":7.63,"volume":1169714.0,"amount":905543616.0},{"date":"2025-01-06","open":7.6,"high":7.69,"low":7.31,"close":7.39,"volume":1094350.0,"amount":818478976.0},{"date":"2025-01-07","open":7.44,"high":7.69,"low":7.42,"close":7.64,"volume":1234483.0,"amount":937145408.0},{"date":"2025-01-08","open":7.58,"high":7.58,"low":7.23,"close":7.49,"volume":1265135.0,"amount":939464384.0},{"date":"2025-01-09","open":7.45,"high":7.68,"low":7.41,"close":7.6,"volume":1075736.0,"amount":817503872.0},{"date":"2025-01-10","open":7.55,"high":7.73,"low":7.48,"close":7.48,"volume":1459540.0,"amount":1110896512.0},{"date":"2025-01-13","open":7.3,"high":7.62,"low":7.26,"close":7.48,"volume":812665.0,"amount":605050944.0},{"date":"2025-01-14","open":7.48,"high":8.2,"low":7.48,"close":8.11,"volume":2160683.0,"amount":1700350720.0},{"date":"2025-01-15","open":8.13,"high":8.24,"low":7.99,"close":8.05,"volume":1734536.0,"amount":1401233920.0},{"date":"2025-01-16","open":8.15,"high":8.18,"low":7.93,"close":8.06,"volume":1321247.0,"amount":1064797248.0},{"date":"2025-01-17","open":7.95,"high":8.1,"low":7.94,"close":8.02,"volume":816751.0,"amount":655220800.0},{"date":"2025-01-20","open":8.1,"high":8.5,"low":8.1,"close":8.29,"volume":1950005.0,"amount":1631517696.0},{"date":"2025-01-21","open":8.35,"high":8.54,"low":8.22,"close":8.5,"volume":1714712.0,"amount":1439717632.0},{"date":"2025-01-22","open":8.45,"high":8.65,"low":8.4,"close":8.48,"volume":1500071.0,"amount":1278376704.0},{"date":"2025-01-23","open":8.6,"high":8.63,"low":8.3,"close":8.32,"volume":1424382.0,"amount":1204855424.0},{"date":"2025-01-24","open":8.3,"high":8.85,"low":8.21,"close":8.77,"volume":2606768.0,"amount":2235936512.0},{"date":"2025-01-27","open":8.77,"high":8.77,"low":8.48,"close":8.51,"volume":1267375.0,"amount":1085490816.0},{"date":"2025-02-05","open":8.79,"high":9.05,"low":8.7,"close":8.88,"volume":2571797.0,"amount":2278337792.0},{"date":"2025-02-06","open":8.95,"high":9.77,"low":8.91,"close":9.77,"volume":2813984.0,"amount":2666952704.0},{"date":"2025-02-07","open":10.02,"high":10.5,"low":9.92,"close":10.16,"volume":7241520.0,"amount":7361044480.0},{"date":"2025-02-10","open":10.19,"high":10.22,"low":9.68,"close":9.8,"volume":4848955.0,"amount":4768970240.0},{"date":"2025-02-11","open":9.76,"high":9.94,"low":9.7,"close":9.79,"volume":2885994.0,"amount":2832995840.0},{"date":"2025-02-12","open":9.98,"high":10.06,"low":9.71,"close":9.91,"volume":3290051.0,"amount":3245808128.0},{"date":"2025-02-13","open":9.88,"high":9.98,"low":9.57,"close":9.61,"volume":3139361.0,"amount":3055558400.0},{"date":"2025-02-14","open":9.63,"high":10.12,"low":9.63,"close":9.79,"volume":3465186.0,"amount":3431273472.0},{"date":"2025-02-17","open":9.79,"high":10.02,"low":9.7,"close":9.95,"volume":3100290.0,"amount":3058484480.0},{"date":"2025-02-18","open":9.89,"high":10.1,"low":9.4,"close":9.48,"volume":3052245.0,"amount":2968072704.0},{"date":"2025-02-19","open":9.48,"high":10.04,"low":9.46,"close":9.99,"volume":3528515.0,"amount":3471138048.0},{"date":"2025-02-20","open":10.06,"high":10.93,"low":9.93,"close":10.6,"volume":6000160.0,"amount":6275098624.0},{"date":"2025-02-21","open":10.59,"high":11.49,"low":10.5,"close":10.68,"volume":7311627.0,"amount":7975562240.0},{"date":"2025-02-24","open":10.63,"high":10.95,"low":10.33,"close":10.45,"volume":3487618.0,"amount":3659223296.0},{"date":"2025-02-25","open":10.27,"high":10.8,"low":10.18,"close":10.41,"volume":3331994.0,"amount":3482420224.0},{"date":"2025-02-26","open":10.42,"high":11.19,"low":10.3,"close":10.78,"volume":4313917.0,"amount":4647592448.0},{"date":"2025-02-27","open":10.68,"high":10.84,"low":10.2,"close":10.43,"volume":3146084.0,"amount":3287041280.0},{"date":"2025-02-28","open":10.35,"high":10.39,"low":9.67,"close":9.72,"volume":2588987.0,"amount":2580330240.0},{"date":"2025-03-03","open":9.84,"high":9.9,"low":9.45,"close":9.58,"volume":1708491.0,"amount":1650849792.0},{"date":"2025-03-04","open":9.46,"high":9.98,"low":9.43,"close":9.85,"volume":1907951.0,"amount":1871581568.0},{"date":"2025-03-05","open":9.82,"high":9.91,"low":9.75,"close":9.89,"volume":1337808.0,"amount":1316231040.0},{"date":"2025-03-06","open":9.96,"high":10.28,"low":9.91,"close":10.1,"volume":1885077.0,"amount":1901547904.0},{"date":"2025-03-07","open":10.06,"high":10.37,"low":9.99,"close":10.09,"volume":1874471.0,"amount":1908064256.0},{"date":"2025-03-10","open":10.28,"high":10.45,"low":10.01,"close":10.1,"volume":1673761.0,"amount":1703586688.0},{"date":"2025-03-11","open":9.9,"high":10.12,"low":9.81,"close":9.98,"volume":1324389.0,"amount":1317919360.0},{"date":"2025-03-12","open":10.05,"high":10.25,"low":9.85,"close":10.1,"volume":1808573.0,"amount":1821788544.0},{"date":"2025-03-13","open":10.0,"high":10.05,"low":9.46,"close":9.64,"volume":2332502.0,"amount":2257575424.0},{"date":"2025-03-14","open":9.55,"high":9.84,"low":9.47,"close":9.77,"volume":1339067.0,"amount":1297258880.0},{"date":"2025-03-17","open":9.81,"high":9.85,"low":9.69,"close":9.78,"volume":1024291.0,"amount":1002051072.0},{"date":"2025-03-18","open":9.78,"high":9.97,"low":9.73,"close":9.85,"volume":1006508.0,"amount":992310848.0},{"date":"2025-03-19","open":9.77,"high":9.84,"low":9.62,"close":9.73,"volume":978581.0,"amount":950199936.0},{"date":"2025-03-20","open":9.7,"high":9.76,"low":9.6,"close":9.61,"volume":859489.0,"amount":831625600.0},{"date":"2025-03-21","open":9.5,"high":9.55,"low":9.1,"close":9.13,"volume":1706057.0,"amount":1582559104.0},{"date":"2025-03-24","open":9.12,"high":9.33,"low":8.94,"close":9.18,"volume":1297437.0,"amount":1183834368.0},{"date":"2025-03-25","open":9.19,"high":9.21,"low":8.97,"close":9.03,"volume":848767.0,"amount":768525376.0},{"date":"2025-03-26","open":9.02,"high":9.19,"low":8.98,"close":9.16,"volume":809716.0,"amount":738709632.0},{"date":"2025-03-27","open":9.08,"high":9.26,"low":8.98,"close":9.15,"volume":815944.0,"amount":746704512.0},{"date":"2025-03-28","open":9.13,"high":9.21,"low":9.09,"close":9.16,"volume":604935.0,"amount":553387584.0},{"date":"2025-03-31","open":9.08,"high":9.1,"low":8.91,"close":9.05,"volume":886303.0,"amount":797600064.0},{"date":"2025-04-01","open":9.14,"high":9.23,"low":9.03,"close":9.04,"volume":754137.0,"amount":687243520.0},{"date":"2025-04-02","open":9.0,"high":9.19,"low":8.98,"close":9.1,"volume":611667.0,"amount":555754688.0},{"date":"2025-04-03","open":8.92,"high":8.96,"low":8.35,"close":8.44,"volume":2006400.0,"amount":1724375168.0},{"date":"2025-04-07","open":7.6,"high":7.64,"low":7.6,"close":7.6,"volume":380985.0,"amount":289640096.0},{"date":"2025-04-08","open":6.85,"high":7.06,"low":6.84,"close":6.84,"volume":1992583.0,"amount":1368582912.0},{"date":"2025-04-09","open":6.46,"high":6.87,"low":6.16,"close":6.74,"volume":4141963.0,"amount":2674204928.0},{"date":"2025-04-10","open":7.2,"high":7.34,"low":7.02,"close":7.06,"volume":3080859.0,"amount":2205845248.0},{"date":"2025-04-11","open":6.83,"high":7.36,"low":6.83,"close":7.26,"volume":2279840.0,"amount":1633523968.0},{"date":"2025-04-14","open":7.53,"high":7.65,"low":7.28,"close":7.34,"volume":2751437.0,"amount":2048414336.0},{"date":"2025-04-15","open":7.37,"high":7.37,"low":7.12,"close":7.21,"volume":1512139.0,"amount":1092614144.0},{"date":"2025-04-16","open":7.13,"high":7.17,"low":6.96,"close":7.04,"volume":1253191.0,"amount":883931712.0},{"date":"2025-04-17","open":6.99,"high":7.12,"low":6.96,"close":7.03,"volume":868049.0,"amount":613729280.0},{"date":"2025-04-18","open":7.02,"high":7.18,"low":7.0,"close":7.17,"volume":970365.0,"amount":688948160.0},{"date":"2025-04-21","open":7.27,"high":7.79,"low":7.17,"close":7.57,"volume":2128835.0,"amount":1584346752.0},{"date":"2025-04-22","open":7.57,"high":7.6,"low":7.42,"close":7.43,"volume":1197931.0,"amount":895817280.0},{"date":"2025-04-23","open":7.65,"high":7.92,"low":7.6,"close":7.78,"volume":2380297.0,"amount":1843499648.0},{"date":"2025-04-24","open":7.79,"high":7.84,"low":7.63,"close":7.69,"volume":1175025.0,"amount":906329280.0},{"date":"2025-04-25","open":7.68,"high":7.86,"low":7.67,"close":7.7,"volume":1161807.0,"amount":901134976.0},{"date":"2025-04-28","open":7.65,"high":7.69,"low":7.58,"close":7.61,"volume":712499.0,"amount":543262592.0},{"date":"2025-04-29","open":7.65,"high":7.78,"low":7.57,"close":7.74,"volume":788631.0,"amount":608226368.0},{"date":"2025-04-30","open":7.78,"high":8.05,"low":7.75,"close":7.98,"volume":1504540.0,"amount":1194169216.0},{"date":"2025-05-06","open":8.11,"high":8.21,"low":8.05,"close":8.2,"volume":1386913.0,"amount":1129774720.0},{"date":"2025-05-07","open":8.41,"high":8.45,"low":8.06,"close":8.15,"volume":1311726.0,"amount":1073718016.0},{"date":"2025-05-08","open":8.14,"high":8.33,"low":8.1,"close":8.3,"volume":1104220.0,"amount":912277440.0},{"date":"2025-05-09","open":8.3,"high":8.3,"low":8.06,"close":8.13,"volume":917724.0,"amount":747081856.0},{"date":"2025-05-12","open":8.38,"high":8.5,"low":8.3,"close":8.49,"volume":1595749.0,"amount":1342127616.0},{"date":"2025-05-13","open":8.67,"high":8.76,"low":8.45,"close":8.48,"volume":1755090.0,"amount":1507005312.0},{"date":"2025-05-14","open":8.42,"high":8.52,"low":8.34,"close":8.45,"volume":1013905.0,"amount":853932416.0},{"date":"2025-05-15","open":8.44,"high":8.44,"low":8.23,"close":8.26,"volume":866270.0,"amount":719326784.0},{"date":"2025-05-16","open":8.23,"high":8.37,"low":8.21,"close":8.3,"volume":665620.0,"amount":552259008.0},{"date":"2025-05-19","open":8.3,"high":8.37,"low":8.12,"close":8.28,"volume":705018.0,"amount":578713600.0},{"date":"2025-05-20","open":8.27,"high":8.35,"low":8.18,"close":8.35,"volume":671300.0,"amount":556904064.0},{"date":"2025-05-21","open":8.36,"high":8.4,"low":8.28,"close":8.36,"volume":833944.0,"amount":695714752.0},{"date":"2025-05-22","open":8.32,"high":8.38,"low":8.2,"close":8.22,"volume":726551.0,"amount":601011648.0},{"date":"2025-05-23","open":8.18,"high":8.33,"low":8.09,"close":8.1,"volume":727640.0,"amount":597310080.0},{"date":"2025-05-26","open":8.0,"high":8.13,"low":7.92,"close":8.11,"volume":704529.0,"amount":566794240.0},{"date":"2025-05-27","open":8.07,"high":8.11,"low":7.95,"close":7.98,"volume":587719.0,"amount":470291360.0},{"date":"2025-05-28","open":7.98,"high":8.06,"low":7.95,"close":8.0,"volume":431428.0,"amount":345022720.0},{"date":"2025-05-29","open":8.1,"high":8.26,"low":8.1,"close":8.23,"volume":849223.0,"amount":695515968.0},{"date":"2025-05-30","open":8.11,"high":8.14,"low":7.99,"close":8.06,"volume":777109.0,"amount":624618112.0},{"date":"2025-06-03","open":8.04,"high":8.22,"low":7.98,"close":8.07,"volume":1005337.0,"amount":818108928.0},{"date":"2025-06-04","open":8.07,"high":8.26,"low":8.07,"close":8.2,"volume":871414.0,"amount":715468864.0},{"date":"2025-06-05","open":8.23,"high":8.54,"low":8.18,"close":8.51,"volume":1491415.0,"amount":1253106816.0},{"date":"2025-06-06","open":8.51,"high":8.52,"low":8.39,"close":8.42,"volume":711058.0,"amount":599314048.0},{"date":"2025-06-09","open":8.43,"high":8.5,"low":8.42,"close":8.48,"volume":661367.0,"amount":559882112.0},{"date":"2025-06-10","open":8.49,"high":8.5,"low":8.25,"close":8.36,"volume":841898.0,"amount":702963264.0},{"date":"2025-06-11","open":8.36,"high":8.55,"low":8.36,"close":8.41,"volume":724828.0,"amount":613056960.0},{"date":"2025-06-12","open":8.38,"high":8.49,"low":8.34,"close":8.38,"volume":773797.0,"amount":650997248.0},{"date":"2025-06-13","open":8.32,"high":8.37,"low":8.11,"close":8.19,"volume":1887143.0,"amount":1548117120.0},{"date":"2025-06-16","open":8.11,"high":8.27,"low":8.1,"close":8.2,"volume":726450.0,"amount":595156352.0},{"date":"2025-06-17","open":8.19,"high":8.32,"low":8.16,"close":8.2,"volume":689690.0,"amount":567962688.0},{"date":"2025-06-18","open":8.2,"high":8.55,"low":8.13,"close":8.51,"volume":1657173.0,"amount":1391987584.0},{"date":"2025-06-19","open":8.52,"high":8.58,"low":8.33,"close":8.38,"volume":899890.0,"amount":760241920.0},{"date":"2025-06-20","open":8.36,"high":8.42,"low":8.2,"close":8.2,"volume":725613.0,"amount":599412864.0},{"date":"2025-06-23","open":8.13,"high":8.26,"low":8.1,"close":8.24,"volume":555215.0,"amount":454962944.0},{"date":"2025-06-24","open":8.29,"high":8.45,"low":8.25,"close":8.44,"volume":914395.0,"amount":766831936.0},{"date":"2025-06-25","open":8.42,"high":8.54,"low":8.4,"close":8.53,"volume":1049557.0,"amount":889748800.0},{"date":"2025-06-26","open":8.58,"high":8.62,"low":8.36,"close":8.37,"volume":952038.0,"amount":805057856.0},{"date":"2025-06-27","open":8.52,"high":8.59,"low":8.4,"close":8.51,"volume":1125934.0,"amount":958750720.0},{"date":"2025-06-30","open":8.55,"high":8.63,"low":8.52,"close":8.59,"volume":912144.0,"amount":781924096.0},{"date":"2025-07-01","open":8.59,"high":8.96,"low":8.45,"close":8.87,"volume":1930570.0,"amount":1686306560.0},{"date":"2025-07-02","open":8.86,"high":8.86,"low":8.71,"close":8.74,"volume":1233893.0,"amount":1081975040.0},{"date":"2025-07-03","open":8.75,"high":9.49,"low":8.74,"close":9.33,"volume":3047990.0,"amount":2782615552.0},{"date":"2025-07-04","open":9.24,"high":9.27,"low":9.07,"close":9.2,"volume":1938081.0,"amount":1776806272.0},{"date":"2025-07-07","open":9.1,"high":9.13,"low":8.86,"close":8.9,"volume":1307978.0,"amount":1168301696.0},{"date":"2025-07-08","open":8.89,"high":9.07,"low":8.87,"close":8.98,"volume":1104123.0,"amount":993064256.0},{"date":"2025-07-09","open":9.05,"high":9.27,"low":8.89,"close":8.92,"volume":1215411.0,"amount":1101406720.0},{"date":"2025-07-10","open":8.89,"high":8.94,"low":8.77,"close":8.85,"volume":829757.0,"amount":733486016.0},{"date":"2025-07-11","open":8.84,"high":8.92,"low":8.74,"close":8.87,"volume":814684.0,"amount":720689600.0},{"date":"2025-07-14","open":8.86,"high":8.95,"low":8.82,"close":8.88,"volume":663174.0,"amount":588985792.0},{"date":"2025-07-15","open":8.85,"high":9.08,"low":8.83,"close":9.05,"volume":1315776.0,"amount":1183069312.0},{"date":"2025-07-16","open":9.01,"high":9.16,"low":8.93,"close":9.08,"volume":969017.0,"amount":878041216.0},{"date":"2025-07-17","open":9.05,"high":9.39,"low":9.0,"close":9.35,"volume":1825368.0,"amount":1689159040.0},{"date":"2025-07-18","open":9.35,"high":9.37,"low":9.11,"close":9.17,"volume":1259168.0,"amount":1157732992.0},{"date":"2025-07-21","open":9.16,"high":9.22,"low":9.1,"close":9.19,"volume":760085.0,"amount":696964224.0},{"date":"2025-07-22","open":9.19,"high":9.19,"low":9.02,"close":9.08,"volume":943300.0,"amount":856239040.0},{"date":"2025-07-23","open":9.03,"high":9.09,"low":8.98,"close":8.99,"volume":740655.0,"amount":668370752.0},{"date":"2025-07-24","open":9.01,"high":9.08,"low":9.0,"close":9.08,"volume":768316.0,"amount":695159360.0},{"date":"2025-07-25","open":9.08,"high":9.19,"low":9.05,"close":9.17,"volume":912978.0,"amount":833911616.0},{"date":"2025-07-28","open":9.22,"high":9.25,"low":9.11,"close":9.17,"volume":757891.0,"amount":694265216.0},{"date":"2025-07-29","open":9.11,"high":9.17,"low":8.98,"close":9.17,"volume":901138.0,"amount":817439488.0},{"date":"2025-07-30","open":9.12,"high":9.13,"low":8.93,"close":8.98,"volume":853440.0,"amount":770403840.0},{"date":"2025-07-31","open":8.91,"high":9.23,"low":8.89,"close":9.01,"volume":1248025.0,"amount":1133657472.0},{"date":"2025-08-01","open":8.98,"high":9.38,"low":8.9,"close":9.18,"volume":1774541.0,"amount":1632054784.0},{"date":"2025-08-04","open":9.18,"high":9.2,"low":9.02,"close":9.15,"volume":972615.0,"amount":885166656.0},{"date":"2025-08-05","open":9.19,"high":9.35,"low":9.16,"close":9.33,"volume":1565707.0,"amount":1453449728.0},{"date":"2025-08-06","open":9.38,"high":9.76,"low":9.23,"close":9.67,"volume":2738584.0,"amount":2621528064.0},{"date":"2025-08-07","open":9.8,"high":10.05,"low":9.57,"close":9.59,"volume":2581478.0,"amount":2515957760.0},{"date":"2025-08-08","open":9.5,"high":9.65,"low":9.45,"close":9.48,"volume":1303425.0,"amount":1242557184.0},{"date":"2025-08-11","open":9.58,"high":9.92,"low":9.58,"close":9.89,"volume":2115232.0,"amount":2073284352.0},{"date":"2025-08-12","open":9.97,"high":10.25,"low":9.83,"close":10.01,"volume":2486655.0,"amount":2504848896.0},{"date":"2025-08-13","open":10.01,"high":10.08,"low":9.86,"close":10.03,"volume":1801905.0,"amount":1798233728.0},{"date":"2025-08-14","open":10.03,"high":10.18,"low":9.8,"close":10.0,"volume":2093809.0,"amount":2088818432.0},{"date":"2025-08-15","open":9.97,"high":10.24,"low":9.91,"close":10.12,"volume":1631295.0,"amount":1647463424.0},{"date":"2025-08-18","open":10.45,"high":11.13,"low":10.3,"close":11.13,"volume":4287785.0,"amount":4670391808.0},{"date":"2025-08-19","open":11.4,"high":12.24,"low":11.28,"close":12.24,"volume":6234616.0,"amount":7297420288.0},{"date":"2025-08-20","open":12.66,"high":13.3,"low":12.01,"close":13.1,"volume":7022882.0,"amount":8908626944.0},{"date":"2025-08-21","open":13.1,"high":13.15,"low":12.0,"close":12.16,"volume":6458948.0,"amount":8051412992.0},{"date":"2025-08-22","open":12.01,"high":12.38,"low":11.96,"close":12.33,"volume":4568978.0,"amount":5561991680.0},{"date":"2025-08-25","open":12.42,"high":13.56,"low":12.19,"close":13.56,"volume":6885409.0,"amount":8994489344.0},{"date":"2025-08-26","open":14.01,"high":14.92,"low":13.88,"close":14.92,"volume":5751652.0,"amount":8277110272.0},{"date":"2025-08-27","open":15.53,"high":16.08,"low":14.68,"close":14.78,"volume":9617041.0,"amount":14682534912.0},{"date":"2025-08-28","open":14.45,"high":16.26,"low":14.44,"close":16.26,"volume":7875027.0,"amount":11987649536.0},{"date":"2025-08-29","open":16.26,"high":16.26,"low":15.26,"close":15.54,"volume":6420704.0,"amount":10036697088.0},{"date":"2025-09-01","open":15.78,"high":16.05,"low":15.13,"close":15.67,"volume":4793258.0,"amount":7468409344.0},{"date":"2025-09-02","open":15.36,"high":15.36,"low":14.29,"close":14.4,"volume":5278126.0,"amount":7715787264.0},{"date":"2025-09-03","open":14.41,"high":14.65,"low":13.78,"close":13.92,"volume":4250854.0,"amount":6022673408.0},{"date":"2025-09-04","open":14.1,"high":14.4,"low":13.2,"close":13.61,"volume":4174080.0,"amount":5775247872.0},{"date":"2025-09-05","open":13.6,"high":14.08,"low":13.27,"close":14.0,"volume":3358826.0,"amount":4631692800.0},{"date":"2025-09-08","open":14.01,"high":14.4,"low":13.81,"close":14.12,"volume":3156300.0,"amount":4440464384.0},{"date":"2025-09-09","open":14.01,"high":14.3,"low":13.65,"close":13.75,"volume":2751756.0,"amount":3841420800.0},{"date":"2025-09-10","open":13.74,"high":14.05,"low":13.56,"close":13.7,"volume":2308118.0,"amount":3184312832.0},{"date":"2025-09-11","open":13.57,"high":14.88,"low":13.38,"close":14.54,"volume":5086302.0,"amount":7257254400.0},{"date":"2025-09-12","open":14.38,"high":14.81,"low":14.21,"close":14.35,"volume":3794028.0,"amount":5490009088.0},{"date":"2025-09-15","open":14.4,"high":14.88,"low":14.15,"close":14.67,"volume":3900423.0,"amount":5702048768.0},{"date":"2025-09-16","open":14.5,"high":15.36,"low":14.36,"close":15.35,"volume":4731239.0,"amount":7092611584.0},{"date":"2025-09-17","open":15.34,"high":15.34,"low":14.88,"close":14.98,"volume":3649813.0,"amount":5481741312.0},{"date":"2025-09-18","open":14.9,"high":15.25,"low":14.04,"close":14.49,"volume":4254332.0,"amount":6299937280.0},{"date":"2025-09-19","open":14.3,"high":14.47,"low":13.94,"close":14.03,"volume":2823439.0,"amount":4003390208.0},{"date":"2025-09-22","open":14.42,"high":15.43,"low":14.33,"close":15.31,"volume":6843560.0,"amount":10387804160.0},{"date":"2025-09-23","open":15.16,"high":15.35,"low":14.7,"close":15.19,"volume":4897672.0,"amount":7361693184.0},{"date":"2025-09-24","open":15.1,"high":15.72,"low":14.76,"close":15.63,"volume":4760457.0,"amount":7257039360.0},{"date":"2025-09-25","open":15.63,"high":16.43,"low":15.18,"close":15.92,"volume":5555028.0,"amount":8768245760.0},{"date":"2025-09-26","open":15.64,"high":15.87,"low":14.7,"close":14.71,"volume":3996266.0,"amount":6079425024.0},{"date":"2025-09-29","open":15.02,"high":16.18,"low":15.02,"close":16.18,"volume":5893458.0,"amount":9340590080.0},{"date":"2025-09-30","open":16.58,"high":16.85,"low":16.1,"close":16.31,"volume":6406971.0,"amount":10544707584.0},{"date":"2025-10-09","open":17.0,"high":17.45,"low":16.73,"close":17.18,"volume":4878972.0,"amount":8362871808.0},{"date":"2025-10-10","open":17.1,"high":18.22,"low":15.88,"close":16.04,"volume":6382196.0,"amount":10800674816.0},{"date":"2025-10-13","open":14.8,"high":15.5,"low":14.6,"close":15.3,"volume":4150179.0,"amount":6231897088.0},{"date":"2025-10-14","open":15.81,"high":16.07,"low":15.11,"close":15.51,"volume":3544475.0,"amount":5524433920.0},{"date":"2025-10-15","open":15.4,"high":15.9,"low":14.8,"close":15.66,"volume":3055546.0,"amount":4690669056.0},{"date":"2025-10-16","open":15.47,"high":15.52,"low":15.07,"close":15.11,"volume":1857274.0,"amount":2839393792.0},{"date":"2025-10-17","open":15.02,"high":15.08,"low":14.1,"close":14.13,"volume":2506890.0,"amount":3632142848.0},{"date":"2025-10-20","open":14.5,"high":14.67,"low":14.27,"close":14.38,"volume":1618064.0,"amount":2340941312.0},{"date":"2025-10-21","open":14.67,"high":15.05,"low":14.61,"close":14.99,"volume":2145764.0,"amount":3192317952.0},{"date":"2025-10-22","open":14.84,"high":15.07,"low":14.67,"close":14.76,"volume":1335074.0,"amount":1977261824.0},{"date":"2025-10-23","open":14.67,"high":14.69,"low":14.25,"close":14.61,"volume":1202344.0,"amount":1735633152.0},{"date":"2025-10-24","open":14.8,"high":15.36,"low":14.75,"close":15.29,"volume":2572630.0,"amount":3896593152.0},{"date":"2025-10-27","open":15.58,"high":15.87,"low":15.44,"close":15.81,"volume":2728555.0,"amount":4284237824.0},{"date":"2025-10-28","open":15.81,"high":16.21,"low":15.65,"close":15.85,"volume":2710547.0,"amount":4310554112.0},{"date":"2025-10-29","open":15.98,"high":16.28,"low":15.84,"close":16.19,"volume":2290640.0,"amount":3686176512.0},{"date":"2025-10-30","open":16.49,"high":16.77,"low":15.91,"close":15.93,"volume":2886468.0,"amount":4699104256.0},{"date":"2025-10-31","open":16.14,"high":16.22,"low":15.55,"close":15.63,"volume":2043144.0,"amount":3219173888.0},{"date":"2025-11-03","open":15.45,"high":15.46,"low":14.88,"close":15.21,"volume":1976836.0,"amount":2980762112.0},{"date":"2025-11-04","open":15.22,"high":15.24,"low":14.71,"close":14.84,"volume":1546367.0,"amount":2302731776.0},{"date":"2025-11-05","open":14.47,"high":14.75,"low":14.3,"close":14.62,"volume":1615598.0,"amount":2345337600.0},{"date":"2025-11-06","open":14.62,"high":15.06,"low":14.54,"close":14.98,"volume":1708549.0,"amount":2531112704.0},{"date":"2025-11-07","open":14.82,"high":14.98,"low":14.6,"close":14.78,"volume":1186093.0,"amount":1751876480.0},{"date":"2025-11-10","open":14.79,"high":14.87,"low":14.34,"close":14.44,"volume":1378192.0,"amount":1993426688.0},{"date":"2025-11-11","open":14.52,"high":14.54,"low":13.88,"close":14.0,"volume":1838667.0,"amount":2588174592.0},{"date":"2025-11-12","open":13.92,"high":14.12,"low":13.75,"close":14.05,"volume":1186179.0,"amount":1662283904.0},{"date":"2025-11-13","open":13.95,"high":14.09,"low":13.79,"close":13.99,"volume":1049793.0,"amount":1464713600.0},{"date":"2025-11-14","open":13.81,"high":13.82,"low":13.55,"close":13.55,"volume":1420284.0,"amount":1941960320.0},{"date":"2025-11-17","open":13.4,"high":13.63,"low":13.35,"close":13.49,"volume":1049802.0,"amount":1411910784.0},{"date":"2025-11-18","open":13.44,"high":13.58,"low":13.3,"close":13.38,"volume":863033.0,"amount":1158024960.0},{"date":"2025-11-19","open":13.37,"high":13.59,"low":13.35,"close":13.43,"volume":843772.0,"amount":1137340672.0},{"date":"2025-11-20","open":13.58,"high":13.68,"low":13.29,"close":13.29,"volume":752832.0,"amount":1013793728.0},{"date":"2025-11-21","open":13.09,"high":13.35,"low":12.97,"close":13.0,"volume":1111902.0,"amount":1457047296.0},{"date":"2025-11-24","open":13.05,"high":13.17,"low":12.74,"close":13.05,"volume":1099944.0,"amount":1423800192.0},{"date":"2025-11-25","open":13.16,"high":13.59,"low":13.15,"close":13.41,"volume":1248035.0,"amount":1674482688.0},{"date":"2025-11-26","open":13.35,"high":13.71,"low":13.26,"close":13.52,"volume":1236319.0,"amount":1676872832.0},{"date":"2025-11-27","open":13.58,"high":14.09,"low":13.55,"close":13.66,"volume":1749469.0,"amount":2422233344.0},{"date":"2025-11-28","open":13.6,"high":13.94,"low":13.5,"close":13.9,"volume":1258436.0,"amount":1734306176.0},{"date":"2025-12-01","open":13.93,"high":14.8,"low":13.86,"close":14.48,"volume":2298236.0,"amount":3291022336.0},{"date":"2025-12-02","open":14.49,"high":15.14,"low":14.3,"close":14.96,"volume":2982435.0,"amount":4380074496.0},{"date":"2025-12-03","open":14.87,"high":15.12,"low":14.6,"close":14.72,"volume":1944386.0,"amount":2877782784.0},{"date":"2025-12-04","open":15.09,"high":15.18,"low":14.67,"close":14.74,"volume":1427057.0,"amount":2120520192.0},{"date":"2025-12-05","open":14.65,"high":14.96,"low":14.42,"close":14.81,"volume":1695933.0,"amount":2493394432.0},{"date":"2025-12-08","open":14.79,"high":15.15,"low":14.71,"close":15.08,"volume":2302939.0,"amount":3449779968.0},{"date":"2025-12-09","open":15.02,"high":15.68,"low":14.93,"close":15.33,"volume":2735785.0,"amount":4188430592.0},{"date":"2025-12-10","open":15.24,"high":15.3,"low":14.82,"close":15.18,"volume":1586305.0,"amount":2385443584.0},{"date":"2025-12-11","open":15.3,"high":15.75,"low":15.14,"close":15.36,"volume":2799694.0,"amount":4340509184.0},{"date":"2025-12-12","open":15.2,"high":16.0,"low":15.1,"close":15.7,"volume":3024046.0,"amount":4724020736.0},{"date":"2025-12-15","open":15.43,"high":15.67,"low":15.15,"close":15.19,"volume":1709492.0,"amount":2625247488.0},{"date":"2025-12-16","open":15.03,"high":15.27,"low":14.74,"close":15.0,"volume":1492910.0,"amount":2233546752.0},{"date":"2025-12-17","open":15.16,"high":15.79,"low":15.12,"close":15.72,"volume":2293295.0,"amount":3555454208.0},{"date":"2025-12-18","open":15.55,"high":15.57,"low":14.93,"close":14.94,"volume":2145052.0,"amount":3254241536.0},{"date":"2025-12-19","open":15.14,"high":15.4,"low":14.96,"close":15.34,"volume":1722230.0,"amount":2621760256.0},{"date":"2025-12-22","open":15.33,"high":16.12,"low":15.28,"close":15.95,"volume":2860168.0,"amount":4506577408.0},{"date":"2025-12-23","open":15.95,"high":15.95,"low":15.06,"close":15.52,"volume":4285953.0,"amount":6600299520.0},{"date":"2025-12-24","open":15.88,"high":16.23,"low":15.71,"close":16.0,"volume":3792118.0,"amount":6052164096.0},{"date":"2025-12-25","open":15.95,"high":16.04,"low":15.64,"close":15.84,"volume":2309353.0,"amount":3653166848.0},{"date":"2025-12-26","open":15.8,"high":15.84,"low":15.21,"close":15.4,"volume":2214660.0,"amount":3424978944.0},{"date":"2025-12-29","open":15.48,"high":15.92,"low":15.48,"close":15.56,"volume":2453979.0,"amount":3853912576.0},{"date":"2025-12-30","open":15.33,"high":15.95,"low":15.11,"close":15.83,"volume":3250685.0,"amount":5110173696.0},{"date":"2025-12-31","open":15.9,"high":15.9,"low":15.41,"close":15.54,"volume":2167873.0,"amount":3374212864.0},{"date":"2026-01-05","open":15.59,"high":16.14,"low":15.59,"close":15.93,"volume":2901025.0,"amount":4619785728.0},{"date":"2026-01-06","open":16.09,"high":16.37,"low":15.7,"close":16.0,"volume":3118057.0,"amount":5000334336.0},{"date":"2026-01-07","open":16.23,"high":16.7,"low":15.86,"close":16.17,"volume":4379516.0,"amount":7125174784.0},{"date":"2026-01-08","open":16.17,"high":16.79,"low":15.96,"close":16.43,"volume":3998298.0,"amount":6574045696.0},{"date":"2026-01-09","open":16.31,"high":16.9,"low":16.05,"close":16.66,"volume":3810320.0,"amount":6325295616.0},{"date":"2026-01-12","open":16.7,"high":18.33,"low":16.47,"close":18.33,"volume":5234768.0,"amount":9153412096.0},{"date":"2026-01-13","open":18.7,"high":18.83,"low":16.82,"close":16.9,"volume":6002572.0,"amount":10557464576.0},{"date":"2026-01-14","open":16.81,"high":17.2,"low":16.16,"close":16.33,"volume":4261862.0,"amount":7125815296.0},{"date":"2026-01-15","open":16.1,"high":16.42,"low":16.01,"close":16.14,"volume":1941349.0,"amount":3131088384.0},{"date":"2026-01-16","open":16.29,"high":16.67,"low":16.18,"close":16.51,"volume":2239082.0,"amount":3682836736.0},{"date":"2026-01-19","open":16.08,"high":16.08,"low":15.55,"close":15.85,"volume":2460381.0,"amount":3900176640.0},{"date":"2026-01-20","open":15.8,"high":15.88,"low":15.25,"close":15.42,"volume":2002294.0,"amount":3094041856.0},{"date":"2026-01-21","open":15.25,"high":15.57,"low":15.23,"close":15.4,"volume":1162123.0,"amount":1797212544.0},{"date":"2026-01-22","open":15.58,"high":15.68,"low":15.4,"close":15.52,"volume":1111725.0,"amount":1725831936.0},{"date":"2026-01-23","open":15.52,"high":15.97,"low":15.42,"close":15.89,"volume":1988948.0,"amount":3126774528.0},{"date":"2026-01-26","open":15.82,"high":16.05,"low":15.4,"close":15.42,"volume":1588368.0,"amount":2476319744.0},{"date":"2026-01-27","open":15.34,"high":15.46,"low":14.73,"close":15.33,"volume":1462270.0,"amount":2213367296.0},{"date":"2026-01-28","open":15.4,"high":15.6,"low":14.94,"close":15.38,"volume":1708836.0,"amount":2608273152.0},{"date":"2026-01-29","open":15.28,"high":15.28,"low":14.88,"close":14.89,"volume":1366096.0,"amount":2054547328.0},{"date":"2026-01-30","open":14.79,"high":14.85,"low":14.36,"close":14.64,"volume":1294173.0,"amount":1893239296.0},{"date":"2026-02-02","open":14.66,"high":14.87,"low":14.43,"close":14.45,"volume":902969.0,"amount":1325300608.0},{"date":"2026-02-03","open":14.61,"high":15.0,"low":14.46,"close":14.95,"volume":1157442.0,"amount":1707125120.0},{"date":"2026-02-04","open":14.92,"high":15.05,"low":14.8,"close":15.05,"volume":821541.0,"amount":1226786432.0},{"date":"2026-02-05","open":14.9,"high":15.03,"low":14.73,"close":14.75,"volume":634266.0,"amount":940237760.0},{"date":"2026-02-06","open":14.55,"high":14.93,"low":14.44,"close":14.72,"volume":630836.0,"amount":929558976.0},{"date":"2026-02-09","open":14.9,"high":15.0,"low":14.78,"close":14.98,"volume":1010961.0,"amount":1503021312.0},{"date":"2026-02-10","open":15.13,"high":15.4,"low":15.12,"close":15.3,"volume":1374757.0,"amount":2101084032.0},{"date":"2026-02-11","open":15.29,"high":15.34,"low":15.08,"close":15.1,"volume":750311.0,"amount":1139782656.0},{"date":"2026-02-12","open":15.1,"high":15.36,"low":15.04,"close":15.32,"volume":844000.0,"amount":1287478144.0},{"date":"2026-02-13","open":15.2,"high":15.56,"low":15.15,"close":15.39,"volume":1067040.0,"amount":1646790656.0},{"date":"2026-02-24","open":15.68,"high":15.76,"low":15.37,"close":15.42,"volume":1000658.0,"amount":1547709824.0},{"date":"2026-02-25","open":15.47,"high":15.49,"low":15.26,"close":15.39,"volume":905481.0,"amount":1390044416.0},{"date":"2026-02-26","open":15.43,"high":15.63,"low":15.3,"close":15.53,"volume":1068500.0,"amount":1654841984.0},{"date":"2026-02-27","open":15.39,"high":15.45,"low":15.25,"close":15.38,"volume":828643.0,"amount":1270418816.0},{"date":"2026-03-02","open":14.9,"high":15.15,"low":14.85,"close":15.04,"volume":1236154.0,"amount":1851386240.0},{"date":"2026-03-03","open":15.05,"high":15.13,"low":14.2,"close":14.2,"volume":1447443.0,"amount":2111433088.0},{"date":"2026-03-04","open":13.91,"high":14.35,"low":13.91,"close":14.08,"volume":763102.0,"amount":1080144512.0},{"date":"2026-03-05","open":14.37,"high":14.49,"low":14.24,"close":14.34,"volume":751077.0,"amount":1081153536.0},{"date":"2026-03-06","open":14.31,"high":14.74,"low":14.28,"close":14.48,"volume":743448.0,"amount":1079658112.0},{"date":"2026-03-09","open":14.24,"high":14.24,"low":13.88,"close":14.16,"volume":994260.0,"amount":1393787904.0},{"date":"2026-03-10","open":14.3,"high":14.7,"low":14.3,"close":14.62,"volume":1000503.0,"amount":1450977664.0},{"date":"2026-03-11","open":14.75,"high":15.46,"low":14.71,"close":15.0,"volume":1865709.0,"amount":2829828096.0},{"date":"2026-03-12","open":14.83,"high":15.01,"low":14.52,"close":14.6,"volume":1127298.0,"amount":1655021568.0},{"date":"2026-03-13","open":14.44,"high":14.59,"low":14.31,"close":14.36,"volume":640481.0,"amount":924560000.0},{"date":"2026-03-16","open":14.3,"high":14.56,"low":14.01,"close":14.4,"volume":798622.0,"amount":1135566592.0},{"date":"2026-03-17","open":14.64,"high":14.68,"low":14.08,"close":14.13,"volume":718617.0,"amount":1027881920.0},{"date":"2026-03-18","open":14.2,"high":14.3,"low":14.1,"close":14.25,"volume":510308.0,"amount":724723264.0},{"date":"2026-03-19","open":14.0,"high":14.06,"low":13.81,"close":13.85,"volume":677420.0,"amount":943771200.0},{"date":"2026-03-20","open":13.89,"high":13.98,"low":13.39,"close":13.4,"volume":727533.0,"amount":994627456.0},{"date":"2026-03-23","open":13.1,"high":13.18,"low":12.57,"close":12.65,"volume":1300388.0,"amount":1676293376.0},{"date":"2026-03-24","open":12.85,"high":12.92,"low":12.45,"close":12.88,"volume":846448.0,"amount":1073936896.0},{"date":"2026-03-25","open":12.91,"high":13.45,"low":12.91,"close":13.26,"volume":938502.0,"amount":1240171136.0},{"date":"2026-03-26","open":13.24,"high":13.4,"low":13.11,"close":13.16,"volume":650304.0,"amount":861006336.0},{"date":"2026-03-27","open":12.95,"high":13.29,"low":12.91,"close":13.17,"volume":478977.0,"amount":629598848.0},{"date":"2026-03-30","open":13.0,"high":13.07,"low":12.71,"close":12.94,"volume":728317.0,"amount":938812352.0},{"date":"2026-03-31","open":12.93,"high":13.14,"low":12.81,"close":12.83,"volume":616843.0,"amount":798089088.0},{"date":"2026-04-01","open":13.09,"high":13.13,"low":12.87,"close":12.96,"volume":584386.0,"amount":757850752.0},{"date":"2026-04-02","open":12.85,"high":12.93,"low":12.44,"close":12.54,"volume":741476.0,"amount":937821888.0},{"date":"2026-04-03","open":12.55,"high":12.65,"low":12.29,"close":12.38,"volume":474376.0,"amount":588687872.0},{"date":"2026-04-07","open":12.55,"high":12.68,"low":12.51,"close":12.62,"volume":612039.0,"amount":771973568.0},{"date":"2026-04-08","open":12.94,"high":13.34,"low":12.92,"close":13.33,"volume":1179766.0,"amount":1548861312.0},{"date":"2026-04-09","open":13.15,"high":13.43,"low":13.08,"close":13.29,"volume":845450.0,"amount":1122260224.0},{"date":"2026-04-10","open":13.43,"high":13.74,"low":13.43,"close":13.61,"volume":1035445.0,"amount":1409464832.0},{"date":"2026-04-13","open":13.55,"high":13.95,"low":13.5,"close":13.75,"volume":1040613.0,"amount":1434897024.0},{"date":"2026-04-14","open":13.85,"high":14.05,"low":13.75,"close":13.88,"volume":968978.0,"amount":1346107648.0},{"date":"2026-04-15","open":13.94,"high":14.02,"low":13.53,"close":13.58,"volume":877648.0,"amount":1207354112.0},{"date":"2026-04-16","open":13.72,"high":13.8,"low":13.46,"close":13.74,"volume":784739.0,"amount":1073465024.0},{"date":"2026-04-17","open":13.7,"high":13.89,"low":13.66,"close":13.79,"volume":773016.0,"amount":1066337920.0},{"date":"2026-04-20","open":14.29,"high":14.85,"low":14.03,"close":14.64,"volume":2439697.0,"amount":3518706944.0},{"date":"2026-04-21","open":14.5,"high":14.5,"low":14.16,"close":14.34,"volume":1398491.0,"amount":1996668544.0},{"date":"2026-04-22","open":14.25,"high":15.08,"low":14.21,"close":14.95,"volume":2107536.0,"amount":3139179008.0},{"date":"2026-04-23","open":15.0,"high":15.03,"low":14.45,"close":14.55,"volume":1548822.0,"amount":2267847424.0},{"date":"2026-04-24","open":14.41,"high":14.44,"low":14.08,"close":14.16,"volume":1002629.0,"amount":1423875072.0},{"date":"2026-04-27","open":14.17,"high":14.47,"low":14.04,"close":14.44,"volume":1090981.0,"amount":1563004032.0},{"date":"2026-04-28","open":14.3,"high":14.3,"low":13.9,"close":13.96,"volume":938902.0,"amount":1324109312.0},{"date":"2026-04-29","open":13.87,"high":14.14,"low":13.75,"close":14.03,"volume":744601.0,"amount":1042364864.0},{"date":"2026-04-30","open":14.0,"high":14.16,"low":13.82,"close":14.06,"volume":1030696.0,"amount":1438962944.0},{"date":"2026-05-06","open":14.07,"high":14.29,"low":14.07,"close":14.12,"volume":1094025.0,"amount":1550739456.0},{"date":"2026-05-07","open":14.21,"high":14.59,"low":14.1,"close":14.53,"volume":1433416.0,"amount":2064719360.0},{"date":"2026-05-08","open":14.38,"high":15.2,"low":14.33,"close":15.09,"volume":2400488.0,"amount":3576552704.0},{"date":"2026-05-11","open":15.1,"high":15.35,"low":14.91,"close":15.24,"volume":2069428.0,"amount":3134923264.0},{"date":"2026-05-12","open":15.16,"high":15.16,"low":14.82,"close":14.96,"volume":1322091.0,"amount":1979722752.0},{"date":"2026-05-13","open":14.84,"high":15.38,"low":14.73,"close":15.37,"volume":1726475.0,"amount":2620545536.0},{"date":"2026-05-14","open":15.94,"high":16.89,"low":15.5,"close":16.4,"volume":6035866.0,"amount":9805026304.0},{"date":"2026-05-15","open":16.4,"high":17.88,"low":16.33,"close":16.94,"volume":5854179.0,"amount":10006626304.0},{"date":"2026-05-18","open":17.26,"high":17.43,"low":16.43,"close":17.07,"volume":3992895.0,"amount":6778188288.0},{"date":"2026-05-19","open":17.46,"high":17.63,"low":16.51,"close":16.91,"volume":3141347.0,"amount":5293436416.0},{"date":"2026-05-20","open":16.5,"high":16.74,"low":15.8,"close":16.23,"volume":3565998.0,"amount":5765290496.0},{"date":"2026-05-21","open":16.43,"high":16.72,"low":15.44,"close":15.52,"volume":3733515.0,"amount":6028717056.0},{"date":"2026-05-22","open":15.7,"high":16.47,"low":15.21,"close":16.31,"volume":3101986.0,"amount":4975548928.0},{"date":"2026-05-25","open":16.43,"high":16.44,"low":15.62,"close":16.09,"volume":2567505.0,"amount":4083169792.0},{"date":"2026-05-26","open":16.09,"high":16.45,"low":15.5,"close":15.82,"volume":2302829.0,"amount":3663584512.0},{"date":"2026-05-27","open":15.75,"high":16.1,"low":15.3,"close":15.52,"volume":2130617.0,"amount":3341401600.0},{"date":"2026-05-28","open":15.82,"high":16.13,"low":15.35,"close":15.95,"volume":2769848.0,"amount":4379548672.0},{"date":"2026-05-29","open":15.96,"high":16.13,"low":14.36,"close":14.55,"volume":3547829.0,"amount":5299251712.0},{"date":"2026-06-01","open":14.59,"high":15.43,"low":14.59,"close":14.97,"volume":2622254.0,"amount":3965562112.0},{"date":"2026-06-02","open":14.91,"high":14.97,"low":14.42,"close":14.67,"volume":1485286.0,"amount":2183449088.0},{"date":"2026-06-03","open":14.7,"high":15.4,"low":14.63,"close":14.86,"volume":2183928.0,"amount":3288638464.0},{"date":"2026-06-04","open":14.63,"high":15.13,"low":14.45,"close":14.99,"volume":1509327.0,"amount":2248496640.0},{"date":"2026-06-05","open":14.86,"high":15.55,"low":14.17,"close":15.08,"volume":2738234.0,"amount":4093430016.0},{"date":"2026-06-08","open":14.5,"high":15.01,"low":14.22,"close":14.34,"volume":1906973.0,"amount":2769315328.0},{"date":"2026-06-09","open":14.62,"high":14.9,"low":14.23,"close":14.86,"volume":1864447.0,"amount":2727366912.0},{"date":"2026-06-10","open":14.7,"high":14.72,"low":13.76,"close":13.9,"volume":2157782.0,"amount":3052820992.0},{"date":"2026-06-11","open":13.9,"high":14.01,"low":13.4,"close":13.63,"volume":1474013.0,"amount":2010372224.0},{"date":"2026-06-12","open":13.91,"high":14.43,"low":13.9,"close":14.01,"volume":2334210.0,"amount":3325115392.0},{"date":"2026-06-15","open":14.15,"high":15.06,"low":14.1,"close":15.04,"volume":2025482.0,"amount":2966010880.0},{"date":"2026-06-16","open":15.0,"high":15.95,"low":14.86,"close":15.69,"volume":2250669.0,"amount":3483331072.0},{"date":"2026-06-17","open":15.5,"high":16.33,"low":15.4,"close":15.85,"volume":2166780.0,"amount":3437411072.0},{"date":"2026-06-18","open":15.8,"high":17.24,"low":15.76,"close":16.82,"volume":3637751.0,"amount":6104035328.0},{"date":"2026-06-22","open":16.88,"high":17.1,"low":16.28,"close":16.68,"volume":2567063.0,"amount":4261670400.0},{"date":"2026-06-23","open":17.3,"high":17.5,"low":15.95,"close":16.05,"volume":2729310.0,"amount":4518135808.0},{"date":"2026-06-24","open":15.92,"high":17.66,"low":15.69,"close":17.66,"volume":4315988.0,"amount":7304634880.0},{"date":"2026-06-25","open":18.15,"high":18.28,"low":17.51,"close":17.88,"volume":4444476.0,"amount":7949352960.0},{"date":"2026-06-26","open":17.69,"high":17.85,"low":16.36,"close":16.41,"volume":3890826.0,"amount":6589898240.0},{"date":"2026-06-29","open":16.86,"high":17.3,"low":15.14,"close":15.76,"volume":3686992.0,"amount":5910836736.0},{"date":"2026-06-30","open":15.76,"high":17.34,"low":15.7,"close":17.34,"volume":3031540.0,"amount":5108548608.0}]}